<?xml version="1.0" encoding="utf-8"?>
<!DOCTYPE score-partwise
  PUBLIC '-//Recordare//DTD MusicXML 2.0 Partwise//EN'
  'http://www.musicxml.org/dtds/partwise.dtd'>
<score-partwise>
  <work>
    <work-title>Kommt her zu mir, spricht Gottes Sohn</work-title>
    </work>
  <movement-title>Kommt her zu mir, spricht Gottes Sohn</movement-title>
  <identification>
    <creator type="composer">Bach, Johann Sebastian</creator>
    <creator type="electronic editor">Craig Stuart Sapp</creator>
    <encoding>
      <encoding-date>2018-02-02</encoding-date>
      <software>Music21</software>
      </encoding>
    </identification>
  <defaults>
    <scaling>
      <millimeters>7</millimeters>
      <tenths>40</tenths>
      </scaling>
    </defaults>
  <part-list>
    <score-part id="P2ed3e18347452889dc9390238669f323">
      <part-name>Voice</part-name>
      <part-abbreviation>V</part-abbreviation>
      <score-instrument id="Ib0184dcab4386c6f4e982185b3aca39d">
        <instrument-name>Voice</instrument-name>
        <instrument-abbreviation>V</instrument-abbreviation>
        </score-instrument>
      <midi-instrument id="Ib0184dcab4386c6f4e982185b3aca39d">
        <midi-channel>1</midi-channel>
        <midi-program>53</midi-program>
        </midi-instrument>
      </score-part>
    <score-part id="P66c6d21625c0aa293259087632401317">
      <part-name>Voice</part-name>
      <part-abbreviation>V</part-abbreviation>
      <score-instrument id="I167c76f072d9724671213f70aa39f150">
        <instrument-name>Voice</instrument-name>
        <instrument-abbreviation>V</instrument-abbreviation>
        </score-instrument>
      <midi-instrument id="I167c76f072d9724671213f70aa39f150">
        <midi-channel>3</midi-channel>
        <midi-program>53</midi-program>
        </midi-instrument>
      </score-part>
    <score-part id="P711487e57d50189038d4c01ecde4349a">
      <part-name>Voice</part-name>
      <part-abbreviation>V</part-abbreviation>
      <score-instrument id="I6a905b0aa7234e06f3f05ee4094ecf50">
        <instrument-name>Voice</instrument-name>
        <instrument-abbreviation>V</instrument-abbreviation>
        </score-instrument>
      <midi-instrument id="I6a905b0aa7234e06f3f05ee4094ecf50">
        <midi-channel>5</midi-channel>
        <midi-program>53</midi-program>
        </midi-instrument>
      </score-part>
    <score-part id="Pfe19d3c573608e8df7bcf8995d25180d">
      <part-name>Voice</part-name>
      <part-abbreviation>V</part-abbreviation>
      <score-instrument id="I0817e36d11fc89e4304275f3a3881341">
        <instrument-name>Voice</instrument-name>
        <instrument-abbreviation>V</instrument-abbreviation>
        </score-instrument>
      <midi-instrument id="I0817e36d11fc89e4304275f3a3881341">
        <midi-channel>7</midi-channel>
        <midi-program>53</midi-program>
        </midi-instrument>
      </score-part>
    </part-list>
  <part id="P2ed3e18347452889dc9390238669f323">
    <measure number="0">
      <attributes>
        <divisions>10080</divisions>
        <key>
          <fifths>3</fifths>
          </key>
        <time>
          <beats>4</beats>
          <beat-type>4</beat-type>
          </time>
        <clef>
          <sign>G</sign>
          <line>2</line>
          </clef>
        </attributes>
      <direction>
        <direction-type>
          <metronome parentheses="no">
            <beat-unit>quarter</beat-unit>
            <per-minute>100</per-minute>
            </metronome>
          </direction-type>
        <sound tempo="100" />
        </direction>
      <note>
        <pitch>
          <step>F</step>
          <alter>1</alter>
          <octave>4</octave>
          </pitch>
        <duration>10080</duration>
        <type>quarter</type>
        </note>
      </measure>
    <measure number="1">
      <attributes />
      <note>
        <pitch>
          <step>F</step>
          <alter>1</alter>
          <octave>4</octave>
          </pitch>
        <duration>10080</duration>
        <type>quarter</type>
        </note>
      <note>
        <pitch>
          <step>F</step>
          <alter>1</alter>
          <octave>4</octave>
          </pitch>
        <duration>10080</duration>
        <type>quarter</type>
        </note>
      <note>
        <pitch>
          <step>C</step>
          <alter>1</alter>
          <octave>5</octave>
          </pitch>
        <duration>10080</duration>
        <type>quarter</type>
        </note>
      <note>
        <pitch>
          <step>B</step>
          <octave>4</octave>
          </pitch>
        <duration>10080</duration>
        <type>quarter</type>
        </note>
      <barline location="right">
        <bar-style>regular</bar-style>
        </barline>
      </measure>
    <measure number="2">
      <attributes />
      <note>
        <pitch>
          <step>C</step>
          <alter>1</alter>
          <octave>5</octave>
          </pitch>
        <duration>10080</duration>
        <type>quarter</type>
        </note>
      <note>
        <pitch>
          <step>A</step>
          <octave>4</octave>
          </pitch>
        <duration>10080</duration>
        <type>quarter</type>
        </note>
      <note>
        <pitch>
          <step>G</step>
          <alter>1</alter>
          <octave>4</octave>
          </pitch>
        <duration>10080</duration>
        <type>quarter</type>
        <notations>
          <fermata type="inverted" />
          </notations>
        </note>
      <note>
        <pitch>
          <step>F</step>
          <alter>1</alter>
          <octave>4</octave>
          </pitch>
        <duration>5040</duration>
        <type>eighth</type>
        <beam number="1">begin</beam>
        </note>
      <note>
        <pitch>
          <step>G</step>
          <alter>1</alter>
          <octave>4</octave>
          </pitch>
        <duration>5040</duration>
        <type>eighth</type>
        <beam number="1">end</beam>
        </note>
      <barline location="right">
        <bar-style>regular</bar-style>
        </barline>
      </measure>
    <measure number="3">
      <attributes />
      <note>
        <pitch>
          <step>A</step>
          <octave>4</octave>
          </pitch>
        <duration>10080</duration>
        <type>quarter</type>
        </note>
      <note>
        <pitch>
          <step>G</step>
          <alter>1</alter>
          <octave>4</octave>
          </pitch>
        <duration>10080</duration>
        <type>quarter</type>
        </note>
      <note>
        <pitch>
          <step>A</step>
          <octave>4</octave>
          </pitch>
        <duration>5040</duration>
        <type>eighth</type>
        <beam number="1">begin</beam>
        </note>
      <note>
        <pitch>
          <step>B</step>
          <octave>4</octave>
          </pitch>
        <duration>5040</duration>
        <type>eighth</type>
        <beam number="1">end</beam>
        </note>
      <note>
        <pitch>
          <step>C</step>
          <alter>1</alter>
          <octave>5</octave>
          </pitch>
        <duration>10080</duration>
        <type>quarter</type>
        </note>
      <barline location="right">
        <bar-style>regular</bar-style>
        </barline>
      </measure>
    <measure number="4">
      <attributes />
      <note>
        <pitch>
          <step>B</step>
          <octave>4</octave>
          </pitch>
        <duration>10080</duration>
        <type>quarter</type>
        </note>
      <note>
        <pitch>
          <step>A</step>
          <octave>4</octave>
          </pitch>
        <duration>10080</duration>
        <type>quarter</type>
        </note>
      <note>
        <pitch>
          <step>G</step>
          <alter>1</alter>
          <octave>4</octave>
          </pitch>
        <duration>10080</duration>
        <type>quarter</type>
        <notations>
          <fermata type="inverted" />
          </notations>
        </note>
      <note>
        <pitch>
          <step>A</step>
          <octave>4</octave>
          </pitch>
        <duration>5040</duration>
        <type>eighth</type>
        <beam number="1">begin</beam>
        </note>
      <note>
        <pitch>
          <step>G</step>
          <alter>1</alter>
          <octave>4</octave>
          </pitch>
        <duration>5040</duration>
        <type>eighth</type>
        <beam number="1">end</beam>
        </note>
      <barline location="right">
        <bar-style>regular</bar-style>
        </barline>
      </measure>
    <measure number="5">
      <attributes />
      <note>
        <pitch>
          <step>F</step>
          <alter>1</alter>
          <octave>4</octave>
          </pitch>
        <duration>10080</duration>
        <type>quarter</type>
        </note>
      <note>
        <pitch>
          <step>F</step>
          <alter>1</alter>
          <octave>4</octave>
          </pitch>
        <duration>10080</duration>
        <type>quarter</type>
        </note>
      <note>
        <pitch>
          <step>B</step>
          <octave>4</octave>
          </pitch>
        <duration>5040</duration>
        <type>eighth</type>
        <beam number="1">begin</beam>
        </note>
      <note>
        <pitch>
          <step>A</step>
          <octave>4</octave>
          </pitch>
        <duration>5040</duration>
        <type>eighth</type>
        <beam number="1">end</beam>
        </note>
      <note>
        <pitch>
          <step>G</step>
          <alter>1</alter>
          <octave>4</octave>
          </pitch>
        <duration>5040</duration>
        <type>eighth</type>
        <beam number="1">begin</beam>
        </note>
      <note>
        <pitch>
          <step>A</step>
          <octave>4</octave>
          </pitch>
        <duration>5040</duration>
        <type>eighth</type>
        <beam number="1">end</beam>
        </note>
      <barline location="right">
        <bar-style>regular</bar-style>
        </barline>
      </measure>
    <measure number="6">
      <attributes />
      <note>
        <pitch>
          <step>F</step>
          <alter>1</alter>
          <octave>4</octave>
          </pitch>
        <duration>20160</duration>
        <type>half</type>
        </note>
      <note>
        <pitch>
          <step>E</step>
          <octave>4</octave>
          </pitch>
        <duration>10080</duration>
        <type>quarter</type>
        <notations>
          <fermata type="inverted" />
          </notations>
        </note>
      <note>
        <pitch>
          <step>E</step>
          <octave>4</octave>
          </pitch>
        <duration>10080</duration>
        <type>quarter</type>
        </note>
      <barline location="right">
        <bar-style>regular</bar-style>
        </barline>
      </measure>
    <measure number="7">
      <attributes />
      <note>
        <pitch>
          <step>A</step>
          <octave>4</octave>
          </pitch>
        <duration>10080</duration>
        <type>quarter</type>
        </note>
      <note>
        <pitch>
          <step>G</step>
          <alter>1</alter>
          <octave>4</octave>
          </pitch>
        <duration>10080</duration>
        <type>quarter</type>
        </note>
      <note>
        <pitch>
          <step>A</step>
          <octave>4</octave>
          </pitch>
        <duration>5040</duration>
        <type>eighth</type>
        <beam number="1">begin</beam>
        </note>
      <note>
        <pitch>
          <step>B</step>
          <octave>4</octave>
          </pitch>
        <duration>5040</duration>
        <type>eighth</type>
        <beam number="1">end</beam>
        </note>
      <note>
        <pitch>
          <step>C</step>
          <alter>1</alter>
          <octave>5</octave>
          </pitch>
        <duration>10080</duration>
        <type>quarter</type>
        </note>
      <barline location="right">
        <bar-style>regular</bar-style>
        </barline>
      </measure>
    <measure number="8">
      <attributes />
      <note>
        <pitch>
          <step>B</step>
          <octave>4</octave>
          </pitch>
        <duration>10080</duration>
        <type>quarter</type>
        </note>
      <note>
        <pitch>
          <step>A</step>
          <octave>4</octave>
          </pitch>
        <duration>10080</duration>
        <type>quarter</type>
        </note>
      <note>
        <pitch>
          <step>G</step>
          <alter>1</alter>
          <octave>4</octave>
          </pitch>
        <duration>10080</duration>
        <type>quarter</type>
        <notations>
          <fermata type="inverted" />
          </notations>
        </note>
      <note>
        <pitch>
          <step>F</step>
          <alter>1</alter>
          <octave>4</octave>
          </pitch>
        <duration>5040</duration>
        <type>eighth</type>
        <beam number="1">begin</beam>
        </note>
      <note>
        <pitch>
          <step>G</step>
          <alter>1</alter>
          <octave>4</octave>
          </pitch>
        <duration>5040</duration>
        <type>eighth</type>
        <beam number="1">end</beam>
        </note>
      <barline location="right">
        <bar-style>regular</bar-style>
        </barline>
      </measure>
    <measure number="9">
      <attributes />
      <note>
        <pitch>
          <step>A</step>
          <octave>4</octave>
          </pitch>
        <duration>10080</duration>
        <type>quarter</type>
        </note>
      <note>
        <pitch>
          <step>G</step>
          <alter>1</alter>
          <octave>4</octave>
          </pitch>
        <duration>10080</duration>
        <type>quarter</type>
        </note>
      <note>
        <pitch>
          <step>A</step>
          <octave>4</octave>
          </pitch>
        <duration>5040</duration>
        <type>eighth</type>
        <beam number="1">begin</beam>
        </note>
      <note>
        <pitch>
          <step>B</step>
          <octave>4</octave>
          </pitch>
        <duration>5040</duration>
        <type>eighth</type>
        <beam number="1">end</beam>
        </note>
      <note>
        <pitch>
          <step>C</step>
          <alter>1</alter>
          <octave>5</octave>
          </pitch>
        <duration>10080</duration>
        <type>quarter</type>
        </note>
      <barline location="right">
        <bar-style>regular</bar-style>
        </barline>
      </measure>
    <measure number="10">
      <attributes />
      <note>
        <pitch>
          <step>B</step>
          <octave>4</octave>
          </pitch>
        <duration>10080</duration>
        <type>quarter</type>
        </note>
      <note>
        <pitch>
          <step>A</step>
          <octave>4</octave>
          </pitch>
        <duration>10080</duration>
        <type>quarter</type>
        </note>
      <note>
        <pitch>
          <step>G</step>
          <alter>1</alter>
          <octave>4</octave>
          </pitch>
        <duration>10080</duration>
        <type>quarter</type>
        <notations>
          <fermata type="inverted" />
          </notations>
        </note>
      <note>
        <pitch>
          <step>C</step>
          <alter>1</alter>
          <octave>5</octave>
          </pitch>
        <duration>10080</duration>
        <type>quarter</type>
        </note>
      <barline location="right">
        <bar-style>regular</bar-style>
        </barline>
      </measure>
    <measure number="11">
      <attributes />
      <note>
        <pitch>
          <step>C</step>
          <alter>1</alter>
          <octave>5</octave>
          </pitch>
        <duration>10080</duration>
        <type>quarter</type>
        </note>
      <note>
        <pitch>
          <step>C</step>
          <alter>1</alter>
          <octave>5</octave>
          </pitch>
        <duration>10080</duration>
        <type>quarter</type>
        </note>
      <note>
        <pitch>
          <step>B</step>
          <octave>4</octave>
          </pitch>
        <duration>5040</duration>
        <type>eighth</type>
        <beam number="1">begin</beam>
        </note>
      <note>
        <pitch>
          <step>A</step>
          <octave>4</octave>
          </pitch>
        <duration>5040</duration>
        <type>eighth</type>
        <beam number="1">end</beam>
        </note>
      <note>
        <pitch>
          <step>G</step>
          <alter>1</alter>
          <octave>4</octave>
          </pitch>
        <duration>5040</duration>
        <type>eighth</type>
        <beam number="1">begin</beam>
        </note>
      <note>
        <pitch>
          <step>A</step>
          <octave>4</octave>
          </pitch>
        <duration>5040</duration>
        <type>eighth</type>
        <beam number="1">end</beam>
        </note>
      <barline location="right">
        <bar-style>regular</bar-style>
        </barline>
      </measure>
    <measure number="12">
      <attributes />
      <note>
        <pitch>
          <step>G</step>
          <alter>1</alter>
          <octave>4</octave>
          </pitch>
        <duration>5040</duration>
        <type>eighth</type>
        <beam number="1">begin</beam>
        </note>
      <note>
        <pitch>
          <step>E</step>
          <alter>1</alter>
          <octave>4</octave>
          </pitch>
        <duration>5040</duration>
        <type>eighth</type>
        <accidental>sharp</accidental>
        <beam number="1">end</beam>
        </note>
      <note>
        <pitch>
          <step>F</step>
          <alter>1</alter>
          <octave>4</octave>
          </pitch>
        <duration>5040</duration>
        <type>eighth</type>
        <beam number="1">begin</beam>
        </note>
      <note>
        <pitch>
          <step>G</step>
          <alter>1</alter>
          <octave>4</octave>
          </pitch>
        <duration>5040</duration>
        <type>eighth</type>
        <beam number="1">end</beam>
        </note>
      <note>
        <pitch>
          <step>G</step>
          <alter>1</alter>
          <octave>4</octave>
          </pitch>
        <duration>20160</duration>
        <type>half</type>
        </note>
      <barline location="right">
        <bar-style>regular</bar-style>
        </barline>
      </measure>
    <measure number="13">
      <attributes />
      <note>
        <pitch>
          <step>F</step>
          <alter>1</alter>
          <octave>4</octave>
          </pitch>
        <duration>30240</duration>
        <type>half</type>
        <dot />
        <notations>
          <fermata type="inverted" />
          </notations>
        </note>
      <barline location="right">
        <bar-style>light-light</bar-style>
        </barline>
      </measure>
    </part>
  <part id="P66c6d21625c0aa293259087632401317">
    <measure number="0">
      <attributes>
        <divisions>10080</divisions>
        <key>
          <fifths>3</fifths>
          </key>
        <time>
          <beats>4</beats>
          <beat-type>4</beat-type>
          </time>
        <clef>
          <sign>G</sign>
          <line>2</line>
          </clef>
        </attributes>
      <direction>
        <direction-type>
          <metronome parentheses="no">
            <beat-unit>quarter</beat-unit>
            <per-minute>100</per-minute>
            </metronome>
          </direction-type>
        <sound tempo="100" />
        </direction>
      <note>
        <pitch>
          <step>C</step>
          <alter>1</alter>
          <octave>4</octave>
          </pitch>
        <duration>5040</duration>
        <type>eighth</type>
        <beam number="1">begin</beam>
        </note>
      <note>
        <pitch>
          <step>D</step>
          <octave>4</octave>
          </pitch>
        <duration>5040</duration>
        <type>eighth</type>
        <beam number="1">end</beam>
        </note>
      </measure>
    <measure number="1">
      <attributes />
      <note>
        <pitch>
          <step>C</step>
          <alter>1</alter>
          <octave>4</octave>
          </pitch>
        <duration>10080</duration>
        <type>quarter</type>
        </note>
      <note>
        <pitch>
          <step>C</step>
          <alter>1</alter>
          <octave>4</octave>
          </pitch>
        <duration>5040</duration>
        <type>eighth</type>
        <beam number="1">begin</beam>
        </note>
      <note>
        <pitch>
          <step>B</step>
          <octave>3</octave>
          </pitch>
        <duration>5040</duration>
        <type>eighth</type>
        <beam number="1">end</beam>
        </note>
      <note>
        <pitch>
          <step>C</step>
          <alter>1</alter>
          <octave>4</octave>
          </pitch>
        <duration>10080</duration>
        <type>quarter</type>
        </note>
      <note>
        <pitch>
          <step>D</step>
          <octave>4</octave>
          </pitch>
        <duration>10080</duration>
        <type>quarter</type>
        </note>
      <barline location="right">
        <bar-style>regular</bar-style>
        </barline>
      </measure>
    <measure number="2">
      <attributes />
      <note>
        <pitch>
          <step>C</step>
          <alter>1</alter>
          <octave>4</octave>
          </pitch>
        <duration>10080</duration>
        <type>quarter</type>
        </note>
      <note>
        <pitch>
          <step>C</step>
          <alter>1</alter>
          <octave>4</octave>
          </pitch>
        <duration>10080</duration>
        <type>quarter</type>
        </note>
      <note>
        <pitch>
          <step>C</step>
          <alter>1</alter>
          <octave>4</octave>
          </pitch>
        <duration>10080</duration>
        <type>quarter</type>
        <notations>
          <fermata type="inverted" />
          </notations>
        </note>
      <note>
        <pitch>
          <step>C</step>
          <alter>1</alter>
          <octave>4</octave>
          </pitch>
        <duration>10080</duration>
        <type>quarter</type>
        </note>
      <barline location="right">
        <bar-style>regular</bar-style>
        </barline>
      </measure>
    <measure number="3">
      <attributes />
      <note>
        <pitch>
          <step>F</step>
          <alter>1</alter>
          <octave>4</octave>
          </pitch>
        <duration>10080</duration>
        <type>quarter</type>
        </note>
      <note>
        <pitch>
          <step>E</step>
          <alter>1</alter>
          <octave>4</octave>
          </pitch>
        <duration>10080</duration>
        <type>quarter</type>
        <accidental>sharp</accidental>
        </note>
      <note>
        <pitch>
          <step>F</step>
          <alter>1</alter>
          <octave>4</octave>
          </pitch>
        <duration>10080</duration>
        <type>quarter</type>
        </note>
      <note>
        <pitch>
          <step>E</step>
          <alter>0</alter>
          <octave>4</octave>
          </pitch>
        <duration>5040</duration>
        <type>eighth</type>
        <accidental>natural</accidental>
        <beam number="1">begin</beam>
        </note>
      <note>
        <pitch>
          <step>F</step>
          <alter>1</alter>
          <octave>4</octave>
          </pitch>
        <duration>5040</duration>
        <type>eighth</type>
        <beam number="1">end</beam>
        </note>
      <barline location="right">
        <bar-style>regular</bar-style>
        </barline>
      </measure>
    <measure number="4">
      <attributes />
      <note>
        <pitch>
          <step>G</step>
          <alter>1</alter>
          <octave>4</octave>
          </pitch>
        <duration>10080</duration>
        <type>quarter</type>
        </note>
      <note>
        <pitch>
          <step>F</step>
          <alter>1</alter>
          <octave>4</octave>
          </pitch>
        <duration>10080</duration>
        <type>quarter</type>
        </note>
      <note>
        <pitch>
          <step>E</step>
          <alter>1</alter>
          <octave>4</octave>
          </pitch>
        <duration>10080</duration>
        <type>quarter</type>
        <accidental>sharp</accidental>
        <notations>
          <fermata type="inverted" />
          </notations>
        </note>
      <note>
        <pitch>
          <step>F</step>
          <alter>1</alter>
          <octave>4</octave>
          </pitch>
        <duration>10080</duration>
        <type>quarter</type>
        </note>
      <barline location="right">
        <bar-style>regular</bar-style>
        </barline>
      </measure>
    <measure number="5">
      <attributes />
      <note>
        <pitch>
          <step>B</step>
          <octave>3</octave>
          </pitch>
        <duration>5040</duration>
        <type>eighth</type>
        <beam number="1">begin</beam>
        </note>
      <note>
        <pitch>
          <step>C</step>
          <alter>1</alter>
          <octave>4</octave>
          </pitch>
        <duration>5040</duration>
        <type>eighth</type>
        <beam number="1">end</beam>
        </note>
      <note>
        <pitch>
          <step>D</step>
          <alter>1</alter>
          <octave>4</octave>
          </pitch>
        <duration>10080</duration>
        <type>quarter</type>
        <accidental>sharp</accidental>
        </note>
      <note>
        <pitch>
          <step>D</step>
          <alter>1</alter>
          <octave>4</octave>
          </pitch>
        <duration>10080</duration>
        <type>quarter</type>
        </note>
      <note>
        <pitch>
          <step>E</step>
          <alter>0</alter>
          <octave>4</octave>
          </pitch>
        <duration>10080</duration>
        <type>quarter</type>
        <accidental>natural</accidental>
        </note>
      <barline location="right">
        <bar-style>regular</bar-style>
        </barline>
      </measure>
    <measure number="6">
      <attributes />
      <note>
        <pitch>
          <step>E</step>
          <octave>4</octave>
          </pitch>
        <duration>10080</duration>
        <type>quarter</type>
        </note>
      <note>
        <pitch>
          <step>D</step>
          <alter>1</alter>
          <octave>4</octave>
          </pitch>
        <duration>10080</duration>
        <type>quarter</type>
        <accidental>sharp</accidental>
        </note>
      <note>
        <pitch>
          <step>B</step>
          <octave>3</octave>
          </pitch>
        <duration>10080</duration>
        <type>quarter</type>
        <notations>
          <fermata type="inverted" />
          </notations>
        </note>
      <note>
        <pitch>
          <step>C</step>
          <alter>1</alter>
          <octave>4</octave>
          </pitch>
        <duration>5040</duration>
        <type>eighth</type>
        <beam number="1">begin</beam>
        </note>
      <note>
        <pitch>
          <step>D</step>
          <alter>0</alter>
          <octave>4</octave>
          </pitch>
        <duration>5040</duration>
        <type>eighth</type>
        <accidental>natural</accidental>
        <beam number="1">end</beam>
        </note>
      <barline location="right">
        <bar-style>regular</bar-style>
        </barline>
      </measure>
    <measure number="7">
      <attributes />
      <note>
        <pitch>
          <step>E</step>
          <octave>4</octave>
          </pitch>
        <duration>10080</duration>
        <type>quarter</type>
        </note>
      <note>
        <pitch>
          <step>B</step>
          <octave>3</octave>
          </pitch>
        <duration>10080</duration>
        <type>quarter</type>
        </note>
      <note>
        <pitch>
          <step>C</step>
          <alter>1</alter>
          <octave>4</octave>
          </pitch>
        <duration>5040</duration>
        <type>eighth</type>
        <beam number="1">begin</beam>
        </note>
      <note>
        <pitch>
          <step>D</step>
          <octave>4</octave>
          </pitch>
        <duration>5040</duration>
        <type>eighth</type>
        <beam number="1">end</beam>
        </note>
      <note>
        <pitch>
          <step>E</step>
          <octave>4</octave>
          </pitch>
        <duration>10080</duration>
        <type>quarter</type>
        </note>
      <barline location="right">
        <bar-style>regular</bar-style>
        </barline>
      </measure>
    <measure number="8">
      <attributes />
      <note>
        <pitch>
          <step>E</step>
          <alter>1</alter>
          <octave>4</octave>
          </pitch>
        <duration>10080</duration>
        <type>quarter</type>
        <accidental>sharp</accidental>
        </note>
      <note>
        <pitch>
          <step>F</step>
          <alter>1</alter>
          <octave>4</octave>
          </pitch>
        <duration>10080</duration>
        <type>quarter</type>
        </note>
      <note>
        <pitch>
          <step>E</step>
          <alter>1</alter>
          <octave>4</octave>
          </pitch>
        <duration>10080</duration>
        <type>quarter</type>
        <accidental>sharp</accidental>
        <notations>
          <fermata type="inverted" />
          </notations>
        </note>
      <note>
        <pitch>
          <step>C</step>
          <alter>1</alter>
          <octave>4</octave>
          </pitch>
        <duration>10080</duration>
        <type>quarter</type>
        </note>
      <barline location="right">
        <bar-style>regular</bar-style>
        </barline>
      </measure>
    <measure number="9">
      <attributes />
      <note>
        <pitch>
          <step>B</step>
          <octave>3</octave>
          </pitch>
        <duration>10080</duration>
        <type>quarter</type>
        </note>
      <note>
        <pitch>
          <step>B</step>
          <octave>3</octave>
          </pitch>
        <duration>10080</duration>
        <type>quarter</type>
        </note>
      <note>
        <pitch>
          <step>C</step>
          <alter>1</alter>
          <octave>4</octave>
          </pitch>
        <duration>5040</duration>
        <type>eighth</type>
        <beam number="1">begin</beam>
        </note>
      <note>
        <pitch>
          <step>D</step>
          <octave>4</octave>
          </pitch>
        <duration>5040</duration>
        <type>eighth</type>
        <beam number="1">end</beam>
        </note>
      <note>
        <pitch>
          <step>E</step>
          <alter>0</alter>
          <octave>4</octave>
          </pitch>
        <duration>10080</duration>
        <type>quarter</type>
        <accidental>natural</accidental>
        </note>
      <barline location="right">
        <bar-style>regular</bar-style>
        </barline>
      </measure>
    <measure number="10">
      <attributes />
      <note>
        <pitch>
          <step>D</step>
          <octave>4</octave>
          </pitch>
        <duration>10080</duration>
        <type>quarter</type>
        </note>
      <note>
        <pitch>
          <step>C</step>
          <alter>1</alter>
          <octave>4</octave>
          </pitch>
        <duration>10080</duration>
        <type>quarter</type>
        </note>
      <note>
        <pitch>
          <step>C</step>
          <alter>1</alter>
          <octave>4</octave>
          </pitch>
        <duration>10080</duration>
        <type>quarter</type>
        <notations>
          <fermata type="inverted" />
          </notations>
        </note>
      <note>
        <pitch>
          <step>E</step>
          <alter>1</alter>
          <octave>4</octave>
          </pitch>
        <duration>10080</duration>
        <type>quarter</type>
        <accidental>sharp</accidental>
        </note>
      <barline location="right">
        <bar-style>regular</bar-style>
        </barline>
      </measure>
    <measure number="11">
      <attributes />
      <note>
        <pitch>
          <step>F</step>
          <alter>1</alter>
          <octave>4</octave>
          </pitch>
        <duration>10080</duration>
        <type>quarter</type>
        </note>
      <note>
        <pitch>
          <step>E</step>
          <alter>0</alter>
          <octave>4</octave>
          </pitch>
        <duration>10080</duration>
        <type>quarter</type>
        <accidental>natural</accidental>
        </note>
      <note>
        <pitch>
          <step>D</step>
          <octave>4</octave>
          </pitch>
        <duration>15120</duration>
        <type>quarter</type>
        <dot />
        </note>
      <note>
        <pitch>
          <step>C</step>
          <alter>1</alter>
          <octave>4</octave>
          </pitch>
        <duration>5040</duration>
        <type>eighth</type>
        </note>
      <barline location="right">
        <bar-style>regular</bar-style>
        </barline>
      </measure>
    <measure number="12">
      <attributes />
      <note>
        <pitch>
          <step>D</step>
          <octave>4</octave>
          </pitch>
        <duration>10080</duration>
        <type>quarter</type>
        </note>
      <note>
        <pitch>
          <step>C</step>
          <alter>1</alter>
          <octave>4</octave>
          </pitch>
        <duration>5040</duration>
        <type>eighth</type>
        <beam number="1">begin</beam>
        </note>
      <note>
        <pitch>
          <step>D</step>
          <octave>4</octave>
          </pitch>
        <duration>5040</duration>
        <type>eighth</type>
        <beam number="1">end</beam>
        </note>
      <note>
        <pitch>
          <step>C</step>
          <alter>1</alter>
          <octave>4</octave>
          </pitch>
        <duration>5040</duration>
        <type>eighth</type>
        <beam number="1">begin</beam>
        </note>
      <note>
        <pitch>
          <step>D</step>
          <octave>4</octave>
          </pitch>
        <duration>5040</duration>
        <type>eighth</type>
        <beam number="1">end</beam>
        </note>
      <note>
        <pitch>
          <step>C</step>
          <alter>1</alter>
          <octave>4</octave>
          </pitch>
        <duration>5040</duration>
        <type>eighth</type>
        <beam number="1">begin</beam>
        </note>
      <note>
        <pitch>
          <step>B</step>
          <octave>3</octave>
          </pitch>
        <duration>5040</duration>
        <type>eighth</type>
        <beam number="1">end</beam>
        </note>
      <barline location="right">
        <bar-style>regular</bar-style>
        </barline>
      </measure>
    <measure number="13">
      <attributes />
      <note>
        <pitch>
          <step>A</step>
          <alter>1</alter>
          <octave>3</octave>
          </pitch>
        <duration>30240</duration>
        <type>half</type>
        <dot />
        <accidental>sharp</accidental>
        <notations>
          <fermata type="inverted" />
          </notations>
        </note>
      <barline location="right">
        <bar-style>light-light</bar-style>
        </barline>
      </measure>
    </part>
  <part id="P711487e57d50189038d4c01ecde4349a">
    <measure number="0">
      <attributes>
        <divisions>10080</divisions>
        <key>
          <fifths>3</fifths>
          </key>
        <time>
          <beats>4</beats>
          <beat-type>4</beat-type>
          </time>
        <clef>
          <sign>G</sign>
          <line>2</line>
          <clef-octave-change>-1</clef-octave-change>
          </clef>
        </attributes>
      <direction>
        <direction-type>
          <metronome parentheses="no">
            <beat-unit>quarter</beat-unit>
            <per-minute>100</per-minute>
            </metronome>
          </direction-type>
        <sound tempo="100" />
        </direction>
      <note>
        <pitch>
          <step>A</step>
          <octave>3</octave>
          </pitch>
        <duration>5040</duration>
        <type>eighth</type>
        <beam number="1">begin</beam>
        </note>
      <note>
        <pitch>
          <step>B</step>
          <octave>3</octave>
          </pitch>
        <duration>5040</duration>
        <type>eighth</type>
        <beam number="1">end</beam>
        </note>
      </measure>
    <measure number="1">
      <attributes />
      <note>
        <pitch>
          <step>A</step>
          <octave>3</octave>
          </pitch>
        <duration>5040</duration>
        <type>eighth</type>
        <beam number="1">begin</beam>
        </note>
      <note>
        <pitch>
          <step>G</step>
          <alter>1</alter>
          <octave>3</octave>
          </pitch>
        <duration>5040</duration>
        <type>eighth</type>
        <beam number="1">end</beam>
        </note>
      <note>
        <pitch>
          <step>F</step>
          <alter>1</alter>
          <octave>3</octave>
          </pitch>
        <duration>10080</duration>
        <type>quarter</type>
        </note>
      <note>
        <pitch>
          <step>F</step>
          <alter>1</alter>
          <octave>3</octave>
          </pitch>
        <duration>5040</duration>
        <type>eighth</type>
        <beam number="1">begin</beam>
        </note>
      <note>
        <pitch>
          <step>A</step>
          <octave>3</octave>
          </pitch>
        <duration>5040</duration>
        <type>eighth</type>
        <beam number="1">end</beam>
        </note>
      <note>
        <pitch>
          <step>G</step>
          <alter>1</alter>
          <octave>3</octave>
          </pitch>
        <duration>5040</duration>
        <type>eighth</type>
        <beam number="1">begin</beam>
        </note>
      <note>
        <pitch>
          <step>F</step>
          <alter>1</alter>
          <octave>3</octave>
          </pitch>
        <duration>5040</duration>
        <type>eighth</type>
        <beam number="1">end</beam>
        </note>
      <barline location="right">
        <bar-style>regular</bar-style>
        </barline>
      </measure>
    <measure number="2">
      <attributes />
      <note>
        <pitch>
          <step>G</step>
          <alter>1</alter>
          <octave>3</octave>
          </pitch>
        <duration>10080</duration>
        <type>quarter</type>
        </note>
      <note>
        <pitch>
          <step>F</step>
          <alter>1</alter>
          <octave>3</octave>
          </pitch>
        <duration>10080</duration>
        <type>quarter</type>
        </note>
      <note>
        <pitch>
          <step>E</step>
          <alter>1</alter>
          <octave>3</octave>
          </pitch>
        <duration>10080</duration>
        <type>quarter</type>
        <accidental>sharp</accidental>
        <notations>
          <fermata type="inverted" />
          </notations>
        </note>
      <note>
        <pitch>
          <step>F</step>
          <alter>1</alter>
          <octave>3</octave>
          </pitch>
        <duration>10080</duration>
        <type>quarter</type>
        </note>
      <barline location="right">
        <bar-style>regular</bar-style>
        </barline>
      </measure>
    <measure number="3">
      <attributes />
      <note>
        <pitch>
          <step>C</step>
          <alter>1</alter>
          <octave>4</octave>
          </pitch>
        <duration>10080</duration>
        <type>quarter</type>
        </note>
      <note>
        <pitch>
          <step>C</step>
          <alter>1</alter>
          <octave>4</octave>
          </pitch>
        <duration>10080</duration>
        <type>quarter</type>
        </note>
      <note>
        <pitch>
          <step>C</step>
          <alter>1</alter>
          <octave>4</octave>
          </pitch>
        <duration>10080</duration>
        <type>quarter</type>
        </note>
      <note>
        <pitch>
          <step>C</step>
          <alter>1</alter>
          <octave>4</octave>
          </pitch>
        <duration>10080</duration>
        <type>quarter</type>
        </note>
      <barline location="right">
        <bar-style>regular</bar-style>
        </barline>
      </measure>
    <measure number="4">
      <attributes />
      <note>
        <pitch>
          <step>D</step>
          <octave>4</octave>
          </pitch>
        <duration>10080</duration>
        <type>quarter</type>
        </note>
      <note>
        <pitch>
          <step>C</step>
          <alter>1</alter>
          <octave>4</octave>
          </pitch>
        <duration>10080</duration>
        <type>quarter</type>
        </note>
      <note>
        <pitch>
          <step>C</step>
          <alter>1</alter>
          <octave>4</octave>
          </pitch>
        <duration>10080</duration>
        <type>quarter</type>
        <notations>
          <fermata type="inverted" />
          </notations>
        </note>
      <note>
        <pitch>
          <step>C</step>
          <alter>1</alter>
          <octave>4</octave>
          </pitch>
        <duration>10080</duration>
        <type>quarter</type>
        </note>
      <barline location="right">
        <bar-style>regular</bar-style>
        </barline>
      </measure>
    <measure number="5">
      <attributes />
      <note>
        <pitch>
          <step>F</step>
          <alter>1</alter>
          <octave>3</octave>
          </pitch>
        <duration>10080</duration>
        <type>quarter</type>
        </note>
      <note>
        <pitch>
          <step>B</step>
          <octave>3</octave>
          </pitch>
        <duration>10080</duration>
        <type>quarter</type>
        </note>
      <note>
        <pitch>
          <step>B</step>
          <octave>3</octave>
          </pitch>
        <duration>10080</duration>
        <type>quarter</type>
        </note>
      <note>
        <pitch>
          <step>C</step>
          <alter>1</alter>
          <octave>4</octave>
          </pitch>
        <duration>10080</duration>
        <type>quarter</type>
        </note>
      <barline location="right">
        <bar-style>regular</bar-style>
        </barline>
      </measure>
    <measure number="6">
      <attributes />
      <note>
        <pitch>
          <step>B</step>
          <octave>3</octave>
          </pitch>
        <duration>5040</duration>
        <type>eighth</type>
        <beam number="1">begin</beam>
        </note>
      <note>
        <pitch>
          <step>A</step>
          <octave>3</octave>
          </pitch>
        <duration>2520</duration>
        <type>16th</type>
        <beam number="1">begin</beam>
        </note>
      <note>
        <pitch>
          <step>G</step>
          <alter>1</alter>
          <octave>3</octave>
          </pitch>
        <duration>2520</duration>
        <type>16th</type>
        <beam number="1">end</beam>
        <beam number="2">end</beam>
        </note>
      <note>
        <pitch>
          <step>A</step>
          <octave>3</octave>
          </pitch>
        <duration>10080</duration>
        <type>quarter</type>
        </note>
      <note>
        <pitch>
          <step>G</step>
          <alter>1</alter>
          <octave>3</octave>
          </pitch>
        <duration>10080</duration>
        <type>quarter</type>
        <notations>
          <fermata type="inverted" />
          </notations>
        </note>
      <note>
        <pitch>
          <step>A</step>
          <octave>3</octave>
          </pitch>
        <duration>10080</duration>
        <type>quarter</type>
        </note>
      <barline location="right">
        <bar-style>regular</bar-style>
        </barline>
      </measure>
    <measure number="7">
      <attributes />
      <note>
        <pitch>
          <step>E</step>
          <octave>3</octave>
          </pitch>
        <duration>5040</duration>
        <type>eighth</type>
        <beam number="1">begin</beam>
        </note>
      <note>
        <pitch>
          <step>F</step>
          <alter>1</alter>
          <octave>3</octave>
          </pitch>
        <duration>5040</duration>
        <type>eighth</type>
        <beam number="1">end</beam>
        </note>
      <note>
        <pitch>
          <step>G</step>
          <alter>1</alter>
          <octave>3</octave>
          </pitch>
        <duration>5040</duration>
        <type>eighth</type>
        <beam number="1">begin</beam>
        </note>
      <note>
        <pitch>
          <step>F</step>
          <alter>1</alter>
          <octave>3</octave>
          </pitch>
        <duration>5040</duration>
        <type>eighth</type>
        <beam number="1">end</beam>
        </note>
      <note>
        <pitch>
          <step>E</step>
          <octave>3</octave>
          </pitch>
        <duration>10080</duration>
        <type>quarter</type>
        </note>
      <note>
        <pitch>
          <step>A</step>
          <octave>3</octave>
          </pitch>
        <duration>10080</duration>
        <type>quarter</type>
        </note>
      <barline location="right">
        <bar-style>regular</bar-style>
        </barline>
      </measure>
    <measure number="8">
      <attributes />
      <note>
        <pitch>
          <step>B</step>
          <octave>3</octave>
          </pitch>
        <duration>10080</duration>
        <type>quarter</type>
        </note>
      <note>
        <pitch>
          <step>C</step>
          <alter>1</alter>
          <octave>4</octave>
          </pitch>
        <duration>10080</duration>
        <type>quarter</type>
        </note>
      <note>
        <pitch>
          <step>C</step>
          <alter>1</alter>
          <octave>4</octave>
          </pitch>
        <duration>10080</duration>
        <type>quarter</type>
        <notations>
          <fermata type="inverted" />
          </notations>
        </note>
      <note>
        <pitch>
          <step>A</step>
          <octave>3</octave>
          </pitch>
        <duration>5040</duration>
        <type>eighth</type>
        <beam number="1">begin</beam>
        </note>
      <note>
        <pitch>
          <step>G</step>
          <alter>1</alter>
          <octave>3</octave>
          </pitch>
        <duration>5040</duration>
        <type>eighth</type>
        <beam number="1">end</beam>
        </note>
      <barline location="right">
        <bar-style>regular</bar-style>
        </barline>
      </measure>
    <measure number="9">
      <attributes />
      <note>
        <pitch>
          <step>F</step>
          <alter>1</alter>
          <octave>3</octave>
          </pitch>
        <duration>10080</duration>
        <type>quarter</type>
        </note>
      <note>
        <pitch>
          <step>G</step>
          <alter>1</alter>
          <octave>3</octave>
          </pitch>
        <duration>5040</duration>
        <type>eighth</type>
        <beam number="1">begin</beam>
        </note>
      <note>
        <pitch>
          <step>F</step>
          <alter>1</alter>
          <octave>3</octave>
          </pitch>
        <duration>5040</duration>
        <type>eighth</type>
        <beam number="1">end</beam>
        </note>
      <note>
        <pitch>
          <step>E</step>
          <octave>3</octave>
          </pitch>
        <duration>10080</duration>
        <type>quarter</type>
        </note>
      <note>
        <pitch>
          <step>A</step>
          <octave>3</octave>
          </pitch>
        <duration>10080</duration>
        <type>quarter</type>
        </note>
      <barline location="right">
        <bar-style>regular</bar-style>
        </barline>
      </measure>
    <measure number="10">
      <attributes />
      <note>
        <pitch>
          <step>A</step>
          <octave>3</octave>
          </pitch>
        <duration>5040</duration>
        <type>eighth</type>
        <beam number="1">begin</beam>
        </note>
      <note>
        <pitch>
          <step>G</step>
          <alter>1</alter>
          <octave>3</octave>
          </pitch>
        <duration>5040</duration>
        <type>eighth</type>
        <beam number="1">end</beam>
        </note>
      <note>
        <pitch>
          <step>G</step>
          <alter>1</alter>
          <octave>3</octave>
          </pitch>
        <duration>5040</duration>
        <type>eighth</type>
        <beam number="1">begin</beam>
        </note>
      <note>
        <pitch>
          <step>F</step>
          <alter>1</alter>
          <octave>3</octave>
          </pitch>
        <duration>5040</duration>
        <type>eighth</type>
        <beam number="1">end</beam>
        </note>
      <note>
        <pitch>
          <step>E</step>
          <alter>1</alter>
          <octave>3</octave>
          </pitch>
        <duration>10080</duration>
        <type>quarter</type>
        <accidental>sharp</accidental>
        <notations>
          <fermata type="inverted" />
          </notations>
        </note>
      <note>
        <pitch>
          <step>G</step>
          <alter>1</alter>
          <octave>3</octave>
          </pitch>
        <duration>10080</duration>
        <type>quarter</type>
        </note>
      <barline location="right">
        <bar-style>regular</bar-style>
        </barline>
      </measure>
    <measure number="11">
      <attributes />
      <note>
        <pitch>
          <step>A</step>
          <octave>3</octave>
          </pitch>
        <duration>10080</duration>
        <type>quarter</type>
        </note>
      <note>
        <pitch>
          <step>A</step>
          <alter>1</alter>
          <octave>3</octave>
          </pitch>
        <duration>10080</duration>
        <type>quarter</type>
        <accidental>sharp</accidental>
        </note>
      <note>
        <pitch>
          <step>B</step>
          <octave>3</octave>
          </pitch>
        <duration>15120</duration>
        <type>quarter</type>
        <dot />
        </note>
      <note>
        <pitch>
          <step>C</step>
          <alter>1</alter>
          <octave>4</octave>
          </pitch>
        <duration>5040</duration>
        <type>eighth</type>
        </note>
      <barline location="right">
        <bar-style>regular</bar-style>
        </barline>
      </measure>
    <measure number="12">
      <attributes />
      <note>
        <pitch>
          <step>B</step>
          <octave>3</octave>
          </pitch>
        <duration>10080</duration>
        <type>quarter</type>
        </note>
      <note>
        <pitch>
          <step>A</step>
          <alter>0</alter>
          <octave>3</octave>
          </pitch>
        <duration>5040</duration>
        <type>eighth</type>
        <accidental>natural</accidental>
        <beam number="1">begin</beam>
        </note>
      <note>
        <pitch>
          <step>F</step>
          <alter>1</alter>
          <octave>3</octave>
          </pitch>
        <duration>5040</duration>
        <type>eighth</type>
        <beam number="1">end</beam>
        </note>
      <note>
        <pitch>
          <step>E</step>
          <alter>1</alter>
          <octave>3</octave>
          </pitch>
        <duration>5040</duration>
        <type>eighth</type>
        <accidental>sharp</accidental>
        </note>
      <note>
        <pitch>
          <step>F</step>
          <alter>1</alter>
          <octave>3</octave>
          </pitch>
        <duration>10080</duration>
        <type>quarter</type>
        </note>
      <note>
        <pitch>
          <step>E</step>
          <alter>1</alter>
          <octave>3</octave>
          </pitch>
        <duration>5040</duration>
        <type>eighth</type>
        <accidental>sharp</accidental>
        </note>
      <barline location="right">
        <bar-style>regular</bar-style>
        </barline>
      </measure>
    <measure number="13">
      <attributes />
      <note>
        <pitch>
          <step>C</step>
          <alter>1</alter>
          <octave>3</octave>
          </pitch>
        <duration>30240</duration>
        <type>half</type>
        <dot />
        <notations>
          <fermata type="inverted" />
          </notations>
        </note>
      <barline location="right">
        <bar-style>light-light</bar-style>
        </barline>
      </measure>
    </part>
  <part id="Pfe19d3c573608e8df7bcf8995d25180d">
    <measure number="0">
      <attributes>
        <divisions>10080</divisions>
        <key>
          <fifths>3</fifths>
          </key>
        <time>
          <beats>4</beats>
          <beat-type>4</beat-type>
          </time>
        <clef>
          <sign>F</sign>
          <line>4</line>
          </clef>
        </attributes>
      <direction>
        <direction-type>
          <metronome parentheses="no">
            <beat-unit>quarter</beat-unit>
            <per-minute>100</per-minute>
            </metronome>
          </direction-type>
        <sound tempo="100" />
        </direction>
      <note>
        <pitch>
          <step>F</step>
          <alter>1</alter>
          <octave>2</octave>
          </pitch>
        <duration>10080</duration>
        <type>quarter</type>
        </note>
      </measure>
    <measure number="1">
      <attributes />
      <note>
        <pitch>
          <step>F</step>
          <alter>1</alter>
          <octave>3</octave>
          </pitch>
        <duration>10080</duration>
        <type>quarter</type>
        </note>
      <note>
        <pitch>
          <step>D</step>
          <octave>3</octave>
          </pitch>
        <duration>10080</duration>
        <type>quarter</type>
        </note>
      <note>
        <pitch>
          <step>A</step>
          <octave>2</octave>
          </pitch>
        <duration>10080</duration>
        <type>quarter</type>
        </note>
      <note>
        <pitch>
          <step>B</step>
          <octave>2</octave>
          </pitch>
        <duration>10080</duration>
        <type>quarter</type>
        </note>
      <barline location="right">
        <bar-style>regular</bar-style>
        </barline>
      </measure>
    <measure number="2">
      <attributes />
      <note>
        <pitch>
          <step>E</step>
          <alter>1</alter>
          <octave>2</octave>
          </pitch>
        <duration>10080</duration>
        <type>quarter</type>
        <accidental>sharp</accidental>
        </note>
      <note>
        <pitch>
          <step>F</step>
          <alter>1</alter>
          <octave>2</octave>
          </pitch>
        <duration>10080</duration>
        <type>quarter</type>
        </note>
      <note>
        <pitch>
          <step>C</step>
          <alter>1</alter>
          <octave>3</octave>
          </pitch>
        <duration>10080</duration>
        <type>quarter</type>
        <notations>
          <fermata type="inverted" />
          </notations>
        </note>
      <note>
        <pitch>
          <step>A</step>
          <octave>2</octave>
          </pitch>
        <duration>5040</duration>
        <type>eighth</type>
        <beam number="1">begin</beam>
        </note>
      <note>
        <pitch>
          <step>G</step>
          <alter>1</alter>
          <octave>2</octave>
          </pitch>
        <duration>5040</duration>
        <type>eighth</type>
        <beam number="1">end</beam>
        </note>
      <barline location="right">
        <bar-style>regular</bar-style>
        </barline>
      </measure>
    <measure number="3">
      <attributes />
      <note>
        <pitch>
          <step>F</step>
          <alter>1</alter>
          <octave>2</octave>
          </pitch>
        <duration>10080</duration>
        <type>quarter</type>
        </note>
      <note>
        <pitch>
          <step>C</step>
          <alter>1</alter>
          <octave>3</octave>
          </pitch>
        <duration>10080</duration>
        <type>quarter</type>
        </note>
      <note>
        <pitch>
          <step>F</step>
          <alter>1</alter>
          <octave>3</octave>
          </pitch>
        <duration>5040</duration>
        <type>eighth</type>
        <beam number="1">begin</beam>
        </note>
      <note>
        <pitch>
          <step>G</step>
          <alter>1</alter>
          <octave>3</octave>
          </pitch>
        <duration>5040</duration>
        <type>eighth</type>
        <beam number="1">end</beam>
        </note>
      <note>
        <pitch>
          <step>A</step>
          <octave>3</octave>
          </pitch>
        <duration>10080</duration>
        <type>quarter</type>
        </note>
      <barline location="right">
        <bar-style>regular</bar-style>
        </barline>
      </measure>
    <measure number="4">
      <attributes />
      <note>
        <pitch>
          <step>E</step>
          <alter>1</alter>
          <octave>3</octave>
          </pitch>
        <duration>10080</duration>
        <type>quarter</type>
        <accidental>sharp</accidental>
        </note>
      <note>
        <pitch>
          <step>F</step>
          <alter>1</alter>
          <octave>3</octave>
          </pitch>
        <duration>10080</duration>
        <type>quarter</type>
        </note>
      <note>
        <pitch>
          <step>C</step>
          <alter>1</alter>
          <octave>3</octave>
          </pitch>
        <duration>10080</duration>
        <type>quarter</type>
        <notations>
          <fermata type="inverted" />
          </notations>
        </note>
      <note>
        <pitch>
          <step>F</step>
          <alter>1</alter>
          <octave>3</octave>
          </pitch>
        <duration>5040</duration>
        <type>eighth</type>
        <beam number="1">begin</beam>
        </note>
      <note>
        <pitch>
          <step>E</step>
          <alter>0</alter>
          <octave>3</octave>
          </pitch>
        <duration>5040</duration>
        <type>eighth</type>
        <accidental>natural</accidental>
        <beam number="1">end</beam>
        </note>
      <barline location="right">
        <bar-style>regular</bar-style>
        </barline>
      </measure>
    <measure number="5">
      <attributes />
      <note>
        <pitch>
          <step>D</step>
          <alter>1</alter>
          <octave>3</octave>
          </pitch>
        <duration>5040</duration>
        <type>eighth</type>
        <accidental>sharp</accidental>
        <beam number="1">begin</beam>
        </note>
      <note>
        <pitch>
          <step>C</step>
          <alter>1</alter>
          <octave>3</octave>
          </pitch>
        <duration>5040</duration>
        <type>eighth</type>
        <beam number="1">end</beam>
        </note>
      <note>
        <pitch>
          <step>B</step>
          <octave>2</octave>
          </pitch>
        <duration>5040</duration>
        <type>eighth</type>
        <beam number="1">begin</beam>
        </note>
      <note>
        <pitch>
          <step>A</step>
          <octave>2</octave>
          </pitch>
        <duration>5040</duration>
        <type>eighth</type>
        <beam number="1">end</beam>
        </note>
      <note>
        <pitch>
          <step>G</step>
          <alter>1</alter>
          <octave>2</octave>
          </pitch>
        <duration>10080</duration>
        <type>quarter</type>
        </note>
      <note>
        <pitch>
          <step>C</step>
          <alter>1</alter>
          <octave>3</octave>
          </pitch>
        <duration>5040</duration>
        <type>eighth</type>
        <beam number="1">begin</beam>
        </note>
      <note>
        <pitch>
          <step>A</step>
          <octave>2</octave>
          </pitch>
        <duration>5040</duration>
        <type>eighth</type>
        <beam number="1">end</beam>
        </note>
      <barline location="right">
        <bar-style>regular</bar-style>
        </barline>
      </measure>
    <measure number="6">
      <attributes />
      <note>
        <pitch>
          <step>B</step>
          <octave>2</octave>
          </pitch>
        <duration>20160</duration>
        <type>half</type>
        </note>
      <note>
        <pitch>
          <step>E</step>
          <octave>2</octave>
          </pitch>
        <duration>10080</duration>
        <type>quarter</type>
        <notations>
          <fermata type="inverted" />
          </notations>
        </note>
      <note>
        <pitch>
          <step>A</step>
          <octave>2</octave>
          </pitch>
        <duration>5040</duration>
        <type>eighth</type>
        <beam number="1">begin</beam>
        </note>
      <note>
        <pitch>
          <step>B</step>
          <octave>2</octave>
          </pitch>
        <duration>5040</duration>
        <type>eighth</type>
        <beam number="1">end</beam>
        </note>
      <barline location="right">
        <bar-style>regular</bar-style>
        </barline>
      </measure>
    <measure number="7">
      <attributes />
      <note>
        <pitch>
          <step>C</step>
          <alter>1</alter>
          <octave>3</octave>
          </pitch>
        <duration>5040</duration>
        <type>eighth</type>
        <beam number="1">begin</beam>
        </note>
      <note>
        <pitch>
          <step>D</step>
          <octave>3</octave>
          </pitch>
        <duration>5040</duration>
        <type>eighth</type>
        <beam number="1">end</beam>
        </note>
      <note>
        <pitch>
          <step>E</step>
          <octave>3</octave>
          </pitch>
        <duration>5040</duration>
        <type>eighth</type>
        <beam number="1">begin</beam>
        </note>
      <note>
        <pitch>
          <step>D</step>
          <octave>3</octave>
          </pitch>
        <duration>5040</duration>
        <type>eighth</type>
        <beam number="1">end</beam>
        </note>
      <note>
        <pitch>
          <step>C</step>
          <alter>1</alter>
          <octave>3</octave>
          </pitch>
        <duration>10080</duration>
        <type>quarter</type>
        </note>
      <note>
        <pitch>
          <step>B</step>
          <octave>2</octave>
          </pitch>
        <duration>5040</duration>
        <type>eighth</type>
        <beam number="1">begin</beam>
        </note>
      <note>
        <pitch>
          <step>A</step>
          <octave>2</octave>
          </pitch>
        <duration>5040</duration>
        <type>eighth</type>
        <beam number="1">end</beam>
        </note>
      <barline location="right">
        <bar-style>regular</bar-style>
        </barline>
      </measure>
    <measure number="8">
      <attributes />
      <note>
        <pitch>
          <step>G</step>
          <alter>1</alter>
          <octave>2</octave>
          </pitch>
        <duration>10080</duration>
        <type>quarter</type>
        </note>
      <note>
        <pitch>
          <step>F</step>
          <alter>1</alter>
          <octave>2</octave>
          </pitch>
        <duration>10080</duration>
        <type>quarter</type>
        </note>
      <note>
        <pitch>
          <step>C</step>
          <alter>1</alter>
          <octave>3</octave>
          </pitch>
        <duration>10080</duration>
        <type>quarter</type>
        <notations>
          <fermata type="inverted" />
          </notations>
        </note>
      <note>
        <pitch>
          <step>F</step>
          <alter>1</alter>
          <octave>3</octave>
          </pitch>
        <duration>5040</duration>
        <type>eighth</type>
        <beam number="1">begin</beam>
        </note>
      <note>
        <pitch>
          <step>E</step>
          <octave>3</octave>
          </pitch>
        <duration>5040</duration>
        <type>eighth</type>
        <beam number="1">end</beam>
        </note>
      <barline location="right">
        <bar-style>regular</bar-style>
        </barline>
      </measure>
    <measure number="9">
      <attributes />
      <note>
        <pitch>
          <step>D</step>
          <alter>1</alter>
          <octave>3</octave>
          </pitch>
        <duration>5040</duration>
        <type>eighth</type>
        <accidental>sharp</accidental>
        <beam number="1">begin</beam>
        </note>
      <note>
        <pitch>
          <step>B</step>
          <octave>2</octave>
          </pitch>
        <duration>5040</duration>
        <type>eighth</type>
        <beam number="1">end</beam>
        </note>
      <note>
        <pitch>
          <step>E</step>
          <octave>3</octave>
          </pitch>
        <duration>5040</duration>
        <type>eighth</type>
        <beam number="1">begin</beam>
        </note>
      <note>
        <pitch>
          <step>D</step>
          <alter>0</alter>
          <octave>3</octave>
          </pitch>
        <duration>5040</duration>
        <type>eighth</type>
        <accidental>natural</accidental>
        <beam number="1">end</beam>
        </note>
      <note>
        <pitch>
          <step>C</step>
          <alter>1</alter>
          <octave>3</octave>
          </pitch>
        <duration>5040</duration>
        <type>eighth</type>
        <beam number="1">begin</beam>
        </note>
      <note>
        <pitch>
          <step>B</step>
          <octave>2</octave>
          </pitch>
        <duration>5040</duration>
        <type>eighth</type>
        <beam number="1">end</beam>
        </note>
      <note>
        <pitch>
          <step>A</step>
          <octave>2</octave>
          </pitch>
        <duration>5040</duration>
        <type>eighth</type>
        <beam number="1">begin</beam>
        </note>
      <note>
        <pitch>
          <step>G</step>
          <alter>1</alter>
          <octave>2</octave>
          </pitch>
        <duration>5040</duration>
        <type>eighth</type>
        <beam number="1">end</beam>
        </note>
      <barline location="right">
        <bar-style>regular</bar-style>
        </barline>
      </measure>
    <measure number="10">
      <attributes />
      <note>
        <pitch>
          <step>F</step>
          <alter>1</alter>
          <octave>2</octave>
          </pitch>
        <duration>5040</duration>
        <type>eighth</type>
        <beam number="1">begin</beam>
        </note>
      <note>
        <pitch>
          <step>E</step>
          <alter>1</alter>
          <octave>2</octave>
          </pitch>
        <duration>5040</duration>
        <type>eighth</type>
        <accidental>sharp</accidental>
        <beam number="1">end</beam>
        </note>
      <note>
        <pitch>
          <step>F</step>
          <alter>1</alter>
          <octave>2</octave>
          </pitch>
        <duration>10080</duration>
        <type>quarter</type>
        </note>
      <note>
        <pitch>
          <step>C</step>
          <alter>1</alter>
          <octave>3</octave>
          </pitch>
        <duration>10080</duration>
        <type>quarter</type>
        <notations>
          <fermata type="inverted" />
          </notations>
        </note>
      <note>
        <pitch>
          <step>C</step>
          <alter>1</alter>
          <octave>3</octave>
          </pitch>
        <duration>10080</duration>
        <type>quarter</type>
        </note>
      <barline location="right">
        <bar-style>regular</bar-style>
        </barline>
      </measure>
    <measure number="11">
      <attributes />
      <note>
        <pitch>
          <step>F</step>
          <alter>1</alter>
          <octave>3</octave>
          </pitch>
        <duration>5040</duration>
        <type>eighth</type>
        <beam number="1">begin</beam>
        </note>
      <note>
        <pitch>
          <step>E</step>
          <alter>0</alter>
          <octave>3</octave>
          </pitch>
        <duration>5040</duration>
        <type>eighth</type>
        <accidental>natural</accidental>
        <beam number="1">end</beam>
        </note>
      <note>
        <pitch>
          <step>D</step>
          <octave>3</octave>
          </pitch>
        <duration>5040</duration>
        <type>eighth</type>
        <beam number="1">begin</beam>
        </note>
      <note>
        <pitch>
          <step>C</step>
          <alter>1</alter>
          <octave>3</octave>
          </pitch>
        <duration>5040</duration>
        <type>eighth</type>
        <beam number="1">end</beam>
        </note>
      <note>
        <pitch>
          <step>D</step>
          <octave>3</octave>
          </pitch>
        <duration>5040</duration>
        <type>eighth</type>
        <beam number="1">begin</beam>
        </note>
      <note>
        <pitch>
          <step>C</step>
          <alter>1</alter>
          <octave>3</octave>
          </pitch>
        <duration>5040</duration>
        <type>eighth</type>
        <beam number="1">end</beam>
        </note>
      <note>
        <pitch>
          <step>B</step>
          <octave>2</octave>
          </pitch>
        <duration>5040</duration>
        <type>eighth</type>
        <beam number="1">begin</beam>
        </note>
      <note>
        <pitch>
          <step>A</step>
          <octave>2</octave>
          </pitch>
        <duration>5040</duration>
        <type>eighth</type>
        <beam number="1">end</beam>
        </note>
      <barline location="right">
        <bar-style>regular</bar-style>
        </barline>
      </measure>
    <measure number="12">
      <attributes />
      <note>
        <pitch>
          <step>B</step>
          <octave>2</octave>
          </pitch>
        <duration>5040</duration>
        <type>eighth</type>
        <beam number="1">begin</beam>
        </note>
      <note>
        <pitch>
          <step>G</step>
          <alter>1</alter>
          <octave>2</octave>
          </pitch>
        <duration>5040</duration>
        <type>eighth</type>
        <beam number="1">end</beam>
        </note>
      <note>
        <pitch>
          <step>A</step>
          <octave>2</octave>
          </pitch>
        <duration>5040</duration>
        <type>eighth</type>
        <beam number="1">begin</beam>
        </note>
      <note>
        <pitch>
          <step>B</step>
          <octave>2</octave>
          </pitch>
        <duration>5040</duration>
        <type>eighth</type>
        <beam number="1">end</beam>
        </note>
      <note>
        <pitch>
          <step>C</step>
          <alter>1</alter>
          <octave>3</octave>
          </pitch>
        <duration>5040</duration>
        <type>eighth</type>
        <beam number="1">begin</beam>
        </note>
      <note>
        <pitch>
          <step>B</step>
          <octave>2</octave>
          </pitch>
        <duration>5040</duration>
        <type>eighth</type>
        <beam number="1">end</beam>
        </note>
      <note>
        <pitch>
          <step>C</step>
          <alter>1</alter>
          <octave>3</octave>
          </pitch>
        <duration>10080</duration>
        <type>quarter</type>
        </note>
      <barline location="right">
        <bar-style>regular</bar-style>
        </barline>
      </measure>
    <measure number="13">
      <attributes />
      <note>
        <pitch>
          <step>F</step>
          <alter>1</alter>
          <octave>2</octave>
          </pitch>
        <duration>30240</duration>
        <type>half</type>
        <dot />
        <notations>
          <fermata type="inverted" />
          </notations>
        </note>
      <barline location="right">
        <bar-style>light-light</bar-style>
        </barline>
      </measure>
    </part>
  </score-partwise>
