<?xml version="1.0" encoding="utf-8"?>
<!DOCTYPE score-partwise
  PUBLIC '-//Recordare//DTD MusicXML 2.0 Partwise//EN'
  'http://www.musicxml.org/dtds/partwise.dtd'>
<score-partwise>
  <work>
    <work-title>Es ist das Heil uns kommen her</work-title>
    </work>
  <movement-title>Es ist das Heil uns kommen her</movement-title>
  <identification>
    <creator type="composer">Bach, Johann Sebastian</creator>
    <creator type="electronic editor">Craig Stuart Sapp</creator>
    <encoding>
      <encoding-date>2018-02-02</encoding-date>
      <software>Music21</software>
      </encoding>
    </identification>
  <defaults>
    <scaling>
      <millimeters>7</millimeters>
      <tenths>40</tenths>
      </scaling>
    </defaults>
  <part-list>
    <score-part id="P3db402cba39af3085c74cd0e4ad0c714">
      <part-name>Voice</part-name>
      <part-abbreviation>V</part-abbreviation>
      <score-instrument id="I43e228898ea443c88b4fad8f42427002">
        <instrument-name>Voice</instrument-name>
        <instrument-abbreviation>V</instrument-abbreviation>
        </score-instrument>
      <midi-instrument id="I43e228898ea443c88b4fad8f42427002">
        <midi-channel>1</midi-channel>
        <midi-program>53</midi-program>
        </midi-instrument>
      </score-part>
    <score-part id="Pace2513445634c2f2146156f7e13990e">
      <part-name>Voice</part-name>
      <part-abbreviation>V</part-abbreviation>
      <score-instrument id="I2e20f7b87d7333eff809acc345af44e6">
        <instrument-name>Voice</instrument-name>
        <instrument-abbreviation>V</instrument-abbreviation>
        </score-instrument>
      <midi-instrument id="I2e20f7b87d7333eff809acc345af44e6">
        <midi-channel>3</midi-channel>
        <midi-program>53</midi-program>
        </midi-instrument>
      </score-part>
    <score-part id="P8766420a64a71bbf5e8d866937817256">
      <part-name>Voice</part-name>
      <part-abbreviation>V</part-abbreviation>
      <score-instrument id="I2b7c5745986b5e25b4a86602b8bcb11e">
        <instrument-name>Voice</instrument-name>
        <instrument-abbreviation>V</instrument-abbreviation>
        </score-instrument>
      <midi-instrument id="I2b7c5745986b5e25b4a86602b8bcb11e">
        <midi-channel>5</midi-channel>
        <midi-program>53</midi-program>
        </midi-instrument>
      </score-part>
    <score-part id="P151db4fe8fcd469a0e65634288de4e99">
      <part-name>Voice</part-name>
      <part-abbreviation>V</part-abbreviation>
      <score-instrument id="I903854eeb9ef3eca2417b0e28b4aa11b">
        <instrument-name>Voice</instrument-name>
        <instrument-abbreviation>V</instrument-abbreviation>
        </score-instrument>
      <midi-instrument id="I903854eeb9ef3eca2417b0e28b4aa11b">
        <midi-channel>7</midi-channel>
        <midi-program>53</midi-program>
        </midi-instrument>
      </score-part>
    </part-list>
  <part id="P3db402cba39af3085c74cd0e4ad0c714">
    <measure number="0">
      <attributes>
        <divisions>10080</divisions>
        <key>
          <fifths>6</fifths>
          </key>
        <time>
          <beats>4</beats>
          <beat-type>4</beat-type>
          </time>
        <clef>
          <sign>G</sign>
          <line>2</line>
          </clef>
        </attributes>
      <direction>
        <direction-type>
          <metronome parentheses="no">
            <beat-unit>quarter</beat-unit>
            <per-minute>100</per-minute>
            </metronome>
          </direction-type>
        <sound tempo="100" />
        </direction>
      <note>
        <pitch>
          <step>C</step>
          <alter>1</alter>
          <octave>5</octave>
          </pitch>
        <duration>10080</duration>
        <type>quarter</type>
        </note>
      </measure>
    <measure number="1">
      <attributes />
      <note>
        <pitch>
          <step>C</step>
          <alter>1</alter>
          <octave>5</octave>
          </pitch>
        <duration>10080</duration>
        <type>quarter</type>
        </note>
      <note>
        <pitch>
          <step>C</step>
          <alter>1</alter>
          <octave>5</octave>
          </pitch>
        <duration>10080</duration>
        <type>quarter</type>
        </note>
      <note>
        <pitch>
          <step>C</step>
          <alter>1</alter>
          <octave>5</octave>
          </pitch>
        <duration>5040</duration>
        <type>eighth</type>
        <beam number="1">begin</beam>
        </note>
      <note>
        <pitch>
          <step>D</step>
          <alter>1</alter>
          <octave>5</octave>
          </pitch>
        <duration>5040</duration>
        <type>eighth</type>
        <beam number="1">end</beam>
        </note>
      <note>
        <pitch>
          <step>E</step>
          <alter>0</alter>
          <octave>5</octave>
          </pitch>
        <duration>10080</duration>
        <type>quarter</type>
        <accidental>natural</accidental>
        </note>
      <barline location="right">
        <bar-style>regular</bar-style>
        </barline>
      </measure>
    <measure number="2">
      <attributes />
      <note>
        <pitch>
          <step>D</step>
          <alter>1</alter>
          <octave>5</octave>
          </pitch>
        <duration>10080</duration>
        <type>quarter</type>
        </note>
      <note>
        <pitch>
          <step>C</step>
          <alter>1</alter>
          <octave>5</octave>
          </pitch>
        <duration>10080</duration>
        <type>quarter</type>
        </note>
      <note>
        <pitch>
          <step>B</step>
          <octave>4</octave>
          </pitch>
        <duration>10080</duration>
        <type>quarter</type>
        <notations>
          <fermata type="inverted" />
          </notations>
        </note>
      <note>
        <pitch>
          <step>C</step>
          <alter>1</alter>
          <octave>5</octave>
          </pitch>
        <duration>5040</duration>
        <type>eighth</type>
        <beam number="1">begin</beam>
        </note>
      <note>
        <pitch>
          <step>B</step>
          <octave>4</octave>
          </pitch>
        <duration>5040</duration>
        <type>eighth</type>
        <beam number="1">end</beam>
        </note>
      <barline location="right">
        <bar-style>regular</bar-style>
        </barline>
      </measure>
    <measure number="3">
      <attributes />
      <note>
        <pitch>
          <step>A</step>
          <alter>1</alter>
          <octave>4</octave>
          </pitch>
        <duration>5040</duration>
        <type>eighth</type>
        <beam number="1">begin</beam>
        </note>
      <note>
        <pitch>
          <step>G</step>
          <alter>1</alter>
          <octave>4</octave>
          </pitch>
        <duration>5040</duration>
        <type>eighth</type>
        <beam number="1">end</beam>
        </note>
      <note>
        <pitch>
          <step>F</step>
          <alter>1</alter>
          <octave>4</octave>
          </pitch>
        <duration>5040</duration>
        <type>eighth</type>
        <beam number="1">begin</beam>
        </note>
      <note>
        <pitch>
          <step>G</step>
          <alter>1</alter>
          <octave>4</octave>
          </pitch>
        <duration>5040</duration>
        <type>eighth</type>
        <beam number="1">end</beam>
        </note>
      <note>
        <pitch>
          <step>A</step>
          <alter>1</alter>
          <octave>4</octave>
          </pitch>
        <duration>10080</duration>
        <type>quarter</type>
        </note>
      <note>
        <pitch>
          <step>B</step>
          <alter>1</alter>
          <octave>4</octave>
          </pitch>
        <duration>10080</duration>
        <type>quarter</type>
        <accidental>sharp</accidental>
        </note>
      <barline location="right">
        <bar-style>regular</bar-style>
        </barline>
      </measure>
    <measure number="4">
      <attributes />
      <note>
        <pitch>
          <step>C</step>
          <alter>1</alter>
          <octave>5</octave>
          </pitch>
        <duration>7560</duration>
        <type>eighth</type>
        <dot />
        <beam number="1">begin</beam>
        </note>
      <note>
        <pitch>
          <step>D</step>
          <alter>1</alter>
          <octave>5</octave>
          </pitch>
        <duration>2520</duration>
        <type>16th</type>
        <beam number="1">end</beam>
        <beam number="2">forward hook</beam>
        </note>
      <note>
        <pitch>
          <step>D</step>
          <alter>1</alter>
          <octave>5</octave>
          </pitch>
        <duration>10080</duration>
        <type>quarter</type>
        </note>
      <note>
        <pitch>
          <step>C</step>
          <alter>1</alter>
          <octave>5</octave>
          </pitch>
        <duration>10080</duration>
        <type>quarter</type>
        <notations>
          <fermata type="inverted" />
          </notations>
        </note>
      <barline location="right">
        <bar-style>light-heavy</bar-style>
        </barline>
      </measure>
    <measure number="0">
      <attributes />
      <note>
        <pitch>
          <step>C</step>
          <alter>1</alter>
          <octave>5</octave>
          </pitch>
        <duration>10080</duration>
        <type>quarter</type>
        </note>
      <barline location="right">
        <bar-style>regular</bar-style>
        </barline>
      </measure>
    <measure number="5">
      <attributes />
      <note>
        <pitch>
          <step>F</step>
          <alter>1</alter>
          <octave>5</octave>
          </pitch>
        <duration>10080</duration>
        <type>quarter</type>
        </note>
      <note>
        <pitch>
          <step>E</step>
          <alter>1</alter>
          <octave>5</octave>
          </pitch>
        <duration>10080</duration>
        <type>quarter</type>
        </note>
      <note>
        <pitch>
          <step>D</step>
          <alter>1</alter>
          <octave>5</octave>
          </pitch>
        <duration>10080</duration>
        <type>quarter</type>
        </note>
      <note>
        <pitch>
          <step>E</step>
          <alter>1</alter>
          <octave>5</octave>
          </pitch>
        <duration>10080</duration>
        <type>quarter</type>
        </note>
      <barline location="right">
        <bar-style>regular</bar-style>
        </barline>
      </measure>
    <measure number="6">
      <attributes />
      <note>
        <pitch>
          <step>F</step>
          <alter>1</alter>
          <octave>5</octave>
          </pitch>
        <duration>5040</duration>
        <type>eighth</type>
        <beam number="1">begin</beam>
        </note>
      <note>
        <pitch>
          <step>E</step>
          <alter>1</alter>
          <octave>5</octave>
          </pitch>
        <duration>5040</duration>
        <type>eighth</type>
        <beam number="1">end</beam>
        </note>
      <note>
        <pitch>
          <step>D</step>
          <alter>1</alter>
          <octave>5</octave>
          </pitch>
        <duration>10080</duration>
        <type>quarter</type>
        </note>
      <note>
        <pitch>
          <step>C</step>
          <alter>1</alter>
          <octave>5</octave>
          </pitch>
        <duration>10080</duration>
        <type>quarter</type>
        <notations>
          <fermata type="inverted" />
          </notations>
        </note>
      <note>
        <pitch>
          <step>C</step>
          <alter>1</alter>
          <octave>5</octave>
          </pitch>
        <duration>10080</duration>
        <type>quarter</type>
        </note>
      <barline location="right">
        <bar-style>regular</bar-style>
        </barline>
      </measure>
    <measure number="7">
      <attributes />
      <note>
        <pitch>
          <step>F</step>
          <alter>1</alter>
          <octave>5</octave>
          </pitch>
        <duration>10080</duration>
        <type>quarter</type>
        </note>
      <note>
        <pitch>
          <step>C</step>
          <alter>1</alter>
          <octave>5</octave>
          </pitch>
        <duration>10080</duration>
        <type>quarter</type>
        </note>
      <note>
        <pitch>
          <step>D</step>
          <alter>1</alter>
          <octave>5</octave>
          </pitch>
        <duration>10080</duration>
        <type>quarter</type>
        </note>
      <note>
        <pitch>
          <step>A</step>
          <alter>1</alter>
          <octave>4</octave>
          </pitch>
        <duration>5040</duration>
        <type>eighth</type>
        <beam number="1">begin</beam>
        </note>
      <note>
        <pitch>
          <step>B</step>
          <octave>4</octave>
          </pitch>
        <duration>5040</duration>
        <type>eighth</type>
        <beam number="1">end</beam>
        </note>
      <barline location="right">
        <bar-style>regular</bar-style>
        </barline>
      </measure>
    <measure number="8">
      <attributes />
      <note>
        <pitch>
          <step>C</step>
          <alter>1</alter>
          <octave>5</octave>
          </pitch>
        <duration>10080</duration>
        <type>quarter</type>
        </note>
      <note>
        <pitch>
          <step>B</step>
          <octave>4</octave>
          </pitch>
        <duration>10080</duration>
        <type>quarter</type>
        </note>
      <note>
        <pitch>
          <step>A</step>
          <alter>1</alter>
          <octave>4</octave>
          </pitch>
        <duration>10080</duration>
        <type>quarter</type>
        <notations>
          <fermata type="inverted" />
          </notations>
        </note>
      <note>
        <pitch>
          <step>A</step>
          <alter>1</alter>
          <octave>4</octave>
          </pitch>
        <duration>10080</duration>
        <type>quarter</type>
        </note>
      <barline location="right">
        <bar-style>regular</bar-style>
        </barline>
      </measure>
    <measure number="9">
      <attributes />
      <note>
        <pitch>
          <step>G</step>
          <alter>1</alter>
          <octave>4</octave>
          </pitch>
        <duration>5040</duration>
        <type>eighth</type>
        <beam number="1">begin</beam>
        </note>
      <note>
        <pitch>
          <step>A</step>
          <alter>1</alter>
          <octave>4</octave>
          </pitch>
        <duration>5040</duration>
        <type>eighth</type>
        <beam number="1">end</beam>
        </note>
      <note>
        <pitch>
          <step>B</step>
          <octave>4</octave>
          </pitch>
        <duration>10080</duration>
        <type>quarter</type>
        </note>
      <note>
        <pitch>
          <step>A</step>
          <alter>1</alter>
          <octave>4</octave>
          </pitch>
        <duration>10080</duration>
        <type>quarter</type>
        </note>
      <note>
        <pitch>
          <step>G</step>
          <alter>1</alter>
          <octave>4</octave>
          </pitch>
        <duration>10080</duration>
        <type>quarter</type>
        </note>
      <barline location="right">
        <bar-style>regular</bar-style>
        </barline>
      </measure>
    <measure number="10">
      <attributes />
      <note>
        <pitch>
          <step>D</step>
          <alter>1</alter>
          <octave>4</octave>
          </pitch>
        <duration>10080</duration>
        <type>quarter</type>
        </note>
      <note>
        <pitch>
          <step>E</step>
          <alter>1</alter>
          <octave>4</octave>
          </pitch>
        <duration>10080</duration>
        <type>quarter</type>
        </note>
      <note>
        <pitch>
          <step>F</step>
          <alter>1</alter>
          <octave>4</octave>
          </pitch>
        <duration>10080</duration>
        <type>quarter</type>
        <notations>
          <fermata type="inverted" />
          </notations>
        </note>
      <barline location="right">
        <bar-style>light-light</bar-style>
        </barline>
      </measure>
    </part>
  <part id="Pace2513445634c2f2146156f7e13990e">
    <measure number="0">
      <attributes>
        <divisions>10080</divisions>
        <key>
          <fifths>6</fifths>
          </key>
        <time>
          <beats>4</beats>
          <beat-type>4</beat-type>
          </time>
        <clef>
          <sign>G</sign>
          <line>2</line>
          </clef>
        </attributes>
      <direction>
        <direction-type>
          <metronome parentheses="no">
            <beat-unit>quarter</beat-unit>
            <per-minute>100</per-minute>
            </metronome>
          </direction-type>
        <sound tempo="100" />
        </direction>
      <note>
        <pitch>
          <step>F</step>
          <alter>1</alter>
          <octave>4</octave>
          </pitch>
        <duration>10080</duration>
        <type>quarter</type>
        </note>
      </measure>
    <measure number="1">
      <attributes />
      <note>
        <pitch>
          <step>F</step>
          <alter>1</alter>
          <octave>4</octave>
          </pitch>
        <duration>10080</duration>
        <type>quarter</type>
        </note>
      <note>
        <pitch>
          <step>E</step>
          <alter>1</alter>
          <octave>4</octave>
          </pitch>
        <duration>10080</duration>
        <type>quarter</type>
        </note>
      <note>
        <pitch>
          <step>F</step>
          <alter>1</alter>
          <octave>4</octave>
          </pitch>
        <duration>10080</duration>
        <type>quarter</type>
        </note>
      <note>
        <pitch>
          <step>G</step>
          <alter>1</alter>
          <octave>4</octave>
          </pitch>
        <duration>10080</duration>
        <type>quarter</type>
        </note>
      <barline location="right">
        <bar-style>regular</bar-style>
        </barline>
      </measure>
    <measure number="2">
      <attributes />
      <note>
        <pitch>
          <step>F</step>
          <alter>1</alter>
          <octave>4</octave>
          </pitch>
        <duration>10080</duration>
        <type>quarter</type>
        </note>
      <note>
        <pitch>
          <step>F</step>
          <alter>1</alter>
          <octave>4</octave>
          </pitch>
        <duration>5040</duration>
        <type>eighth</type>
        <beam number="1">begin</beam>
        </note>
      <note>
        <pitch>
          <step>E</step>
          <alter>0</alter>
          <octave>4</octave>
          </pitch>
        <duration>5040</duration>
        <type>eighth</type>
        <accidental>natural</accidental>
        <beam number="1">end</beam>
        </note>
      <note>
        <pitch>
          <step>D</step>
          <alter>1</alter>
          <octave>4</octave>
          </pitch>
        <duration>10080</duration>
        <type>quarter</type>
        <notations>
          <fermata type="inverted" />
          </notations>
        </note>
      <note>
        <pitch>
          <step>C</step>
          <alter>1</alter>
          <octave>4</octave>
          </pitch>
        <duration>10080</duration>
        <type>quarter</type>
        </note>
      <barline location="right">
        <bar-style>regular</bar-style>
        </barline>
      </measure>
    <measure number="3">
      <attributes />
      <note>
        <pitch>
          <step>C</step>
          <alter>1</alter>
          <octave>4</octave>
          </pitch>
        <duration>10080</duration>
        <type>quarter</type>
        </note>
      <note>
        <pitch>
          <step>C</step>
          <alter>1</alter>
          <octave>4</octave>
          </pitch>
        <duration>10080</duration>
        <type>quarter</type>
        </note>
      <note>
        <pitch>
          <step>F</step>
          <alter>1</alter>
          <octave>4</octave>
          </pitch>
        <duration>5040</duration>
        <type>eighth</type>
        <beam number="1">begin</beam>
        </note>
      <note>
        <pitch>
          <step>A</step>
          <alter>1</alter>
          <octave>4</octave>
          </pitch>
        <duration>5040</duration>
        <type>eighth</type>
        <beam number="1">end</beam>
        </note>
      <note>
        <pitch>
          <step>G</step>
          <alter>1</alter>
          <octave>4</octave>
          </pitch>
        <duration>5040</duration>
        <type>eighth</type>
        <beam number="1">begin</beam>
        </note>
      <note>
        <pitch>
          <step>F</step>
          <alter>1</alter>
          <octave>4</octave>
          </pitch>
        <duration>5040</duration>
        <type>eighth</type>
        <beam number="1">end</beam>
        </note>
      <barline location="right">
        <bar-style>regular</bar-style>
        </barline>
      </measure>
    <measure number="4">
      <attributes />
      <note>
        <pitch>
          <step>E</step>
          <alter>1</alter>
          <octave>4</octave>
          </pitch>
        <duration>7560</duration>
        <type>eighth</type>
        <dot />
        <beam number="1">begin</beam>
        </note>
      <note>
        <pitch>
          <step>F</step>
          <alter>1</alter>
          <octave>4</octave>
          </pitch>
        <duration>2520</duration>
        <type>16th</type>
        <beam number="1">end</beam>
        <beam number="2">forward hook</beam>
        </note>
      <note>
        <pitch>
          <step>G</step>
          <alter>1</alter>
          <octave>4</octave>
          </pitch>
        <duration>7560</duration>
        <type>eighth</type>
        <dot />
        <beam number="1">begin</beam>
        </note>
      <note>
        <pitch>
          <step>F</step>
          <alter>1</alter>
          <octave>4</octave>
          </pitch>
        <duration>2520</duration>
        <type>16th</type>
        <beam number="1">end</beam>
        <beam number="2">forward hook</beam>
        </note>
      <note>
        <pitch>
          <step>E</step>
          <alter>1</alter>
          <octave>4</octave>
          </pitch>
        <duration>10080</duration>
        <type>quarter</type>
        <notations>
          <fermata type="inverted" />
          </notations>
        </note>
      <barline location="right">
        <bar-style>light-heavy</bar-style>
        </barline>
      </measure>
    <measure number="0">
      <attributes />
      <note>
        <pitch>
          <step>F</step>
          <alter>1</alter>
          <octave>4</octave>
          </pitch>
        <duration>5040</duration>
        <type>eighth</type>
        <beam number="1">begin</beam>
        </note>
      <note>
        <pitch>
          <step>G</step>
          <alter>1</alter>
          <octave>4</octave>
          </pitch>
        <duration>5040</duration>
        <type>eighth</type>
        <beam number="1">end</beam>
        </note>
      <barline location="right">
        <bar-style>regular</bar-style>
        </barline>
      </measure>
    <measure number="5">
      <attributes />
      <note>
        <pitch>
          <step>A</step>
          <alter>1</alter>
          <octave>4</octave>
          </pitch>
        <duration>10080</duration>
        <type>quarter</type>
        </note>
      <note>
        <pitch>
          <step>G</step>
          <alter>1</alter>
          <octave>4</octave>
          </pitch>
        <duration>10080</duration>
        <type>quarter</type>
        </note>
      <note>
        <pitch>
          <step>G</step>
          <alter>1</alter>
          <octave>4</octave>
          </pitch>
        <duration>5040</duration>
        <type>eighth</type>
        <beam number="1">begin</beam>
        </note>
      <note>
        <pitch>
          <step>F</step>
          <alter>1</alter>
          <octave>4</octave>
          </pitch>
        <duration>5040</duration>
        <type>eighth</type>
        <beam number="1">end</beam>
        </note>
      <note>
        <pitch>
          <step>E</step>
          <alter>1</alter>
          <octave>4</octave>
          </pitch>
        <duration>5040</duration>
        <type>eighth</type>
        <beam number="1">begin</beam>
        </note>
      <note>
        <pitch>
          <step>G</step>
          <alter>1</alter>
          <octave>4</octave>
          </pitch>
        <duration>5040</duration>
        <type>eighth</type>
        <beam number="1">end</beam>
        </note>
      <barline location="right">
        <bar-style>regular</bar-style>
        </barline>
      </measure>
    <measure number="6">
      <attributes />
      <note>
        <pitch>
          <step>C</step>
          <alter>1</alter>
          <octave>4</octave>
          </pitch>
        <duration>5040</duration>
        <type>eighth</type>
        <beam number="1">begin</beam>
        </note>
      <note>
        <pitch>
          <step>A</step>
          <alter>1</alter>
          <octave>4</octave>
          </pitch>
        <duration>5040</duration>
        <type>eighth</type>
        <beam number="1">end</beam>
        </note>
      <note>
        <pitch>
          <step>D</step>
          <alter>1</alter>
          <octave>4</octave>
          </pitch>
        <duration>5040</duration>
        <type>eighth</type>
        <beam number="1">begin</beam>
        </note>
      <note>
        <pitch>
          <step>G</step>
          <alter>1</alter>
          <octave>4</octave>
          </pitch>
        <duration>5040</duration>
        <type>eighth</type>
        <beam number="1">end</beam>
        </note>
      <note>
        <pitch>
          <step>E</step>
          <alter>1</alter>
          <octave>4</octave>
          </pitch>
        <duration>10080</duration>
        <type>quarter</type>
        <notations>
          <fermata type="inverted" />
          </notations>
        </note>
      <note>
        <pitch>
          <step>F</step>
          <alter>1</alter>
          <octave>4</octave>
          </pitch>
        <duration>5040</duration>
        <type>eighth</type>
        <beam number="1">begin</beam>
        </note>
      <note>
        <pitch>
          <step>G</step>
          <alter>1</alter>
          <octave>4</octave>
          </pitch>
        <duration>5040</duration>
        <type>eighth</type>
        <beam number="1">end</beam>
        </note>
      <barline location="right">
        <bar-style>regular</bar-style>
        </barline>
      </measure>
    <measure number="7">
      <attributes />
      <note>
        <pitch>
          <step>A</step>
          <alter>1</alter>
          <octave>4</octave>
          </pitch>
        <duration>5040</duration>
        <type>eighth</type>
        <beam number="1">begin</beam>
        </note>
      <note>
        <pitch>
          <step>B</step>
          <octave>4</octave>
          </pitch>
        <duration>5040</duration>
        <type>eighth</type>
        <beam number="1">end</beam>
        </note>
      <note>
        <pitch>
          <step>A</step>
          <alter>1</alter>
          <octave>4</octave>
          </pitch>
        <duration>5040</duration>
        <type>eighth</type>
        <beam number="1">begin</beam>
        </note>
      <note>
        <pitch>
          <step>G</step>
          <alter>1</alter>
          <octave>4</octave>
          </pitch>
        <duration>5040</duration>
        <type>eighth</type>
        <beam number="1">end</beam>
        </note>
      <note>
        <pitch>
          <step>F</step>
          <alter>1</alter>
          <octave>4</octave>
          </pitch>
        <duration>10080</duration>
        <type>quarter</type>
        </note>
      <note>
        <pitch>
          <step>F</step>
          <alter>1</alter>
          <octave>4</octave>
          </pitch>
        <duration>10080</duration>
        <type>quarter</type>
        </note>
      <barline location="right">
        <bar-style>regular</bar-style>
        </barline>
      </measure>
    <measure number="8">
      <attributes />
      <note>
        <pitch>
          <step>E</step>
          <alter>1</alter>
          <octave>4</octave>
          </pitch>
        <duration>10080</duration>
        <type>quarter</type>
        </note>
      <note>
        <pitch>
          <step>D</step>
          <alter>1</alter>
          <octave>4</octave>
          </pitch>
        <duration>5040</duration>
        <type>eighth</type>
        <beam number="1">begin</beam>
        </note>
      <note>
        <pitch>
          <step>E</step>
          <alter>1</alter>
          <octave>4</octave>
          </pitch>
        <duration>5040</duration>
        <type>eighth</type>
        <beam number="1">end</beam>
        </note>
      <note>
        <pitch>
          <step>F</step>
          <alter>2</alter>
          <octave>4</octave>
          </pitch>
        <duration>10080</duration>
        <type>quarter</type>
        <accidental>double-sharp</accidental>
        <notations>
          <fermata type="inverted" />
          </notations>
        </note>
      <note>
        <pitch>
          <step>F</step>
          <alter>1</alter>
          <octave>4</octave>
          </pitch>
        <duration>10080</duration>
        <type>quarter</type>
        <accidental>sharp</accidental>
        </note>
      <barline location="right">
        <bar-style>regular</bar-style>
        </barline>
      </measure>
    <measure number="9">
      <attributes />
      <note>
        <pitch>
          <step>E</step>
          <alter>1</alter>
          <octave>4</octave>
          </pitch>
        <duration>10080</duration>
        <type>quarter</type>
        </note>
      <note>
        <pitch>
          <step>D</step>
          <alter>1</alter>
          <octave>4</octave>
          </pitch>
        <duration>10080</duration>
        <type>quarter</type>
        </note>
      <note>
        <pitch>
          <step>C</step>
          <alter>1</alter>
          <octave>4</octave>
          </pitch>
        <duration>5040</duration>
        <type>eighth</type>
        <beam number="1">begin</beam>
        </note>
      <note>
        <pitch>
          <step>D</step>
          <alter>1</alter>
          <octave>4</octave>
          </pitch>
        <duration>5040</duration>
        <type>eighth</type>
        <beam number="1">end</beam>
        </note>
      <note>
        <pitch>
          <step>E</step>
          <alter>1</alter>
          <octave>4</octave>
          </pitch>
        <duration>10080</duration>
        <type>quarter</type>
        </note>
      <barline location="right">
        <bar-style>regular</bar-style>
        </barline>
      </measure>
    <measure number="10">
      <attributes />
      <note>
        <pitch>
          <step>D</step>
          <alter>1</alter>
          <octave>4</octave>
          </pitch>
        <duration>10080</duration>
        <type>quarter</type>
        </note>
      <note>
        <pitch>
          <step>C</step>
          <alter>1</alter>
          <octave>4</octave>
          </pitch>
        <duration>5040</duration>
        <type>eighth</type>
        <beam number="1">begin</beam>
        </note>
      <note>
        <pitch>
          <step>B</step>
          <octave>3</octave>
          </pitch>
        <duration>5040</duration>
        <type>eighth</type>
        <beam number="1">end</beam>
        </note>
      <note>
        <pitch>
          <step>A</step>
          <alter>1</alter>
          <octave>3</octave>
          </pitch>
        <duration>10080</duration>
        <type>quarter</type>
        <notations>
          <fermata type="inverted" />
          </notations>
        </note>
      <barline location="right">
        <bar-style>light-light</bar-style>
        </barline>
      </measure>
    </part>
  <part id="P8766420a64a71bbf5e8d866937817256">
    <measure number="0">
      <attributes>
        <divisions>10080</divisions>
        <key>
          <fifths>6</fifths>
          </key>
        <time>
          <beats>4</beats>
          <beat-type>4</beat-type>
          </time>
        <clef>
          <sign>G</sign>
          <line>2</line>
          <clef-octave-change>-1</clef-octave-change>
          </clef>
        </attributes>
      <direction>
        <direction-type>
          <metronome parentheses="no">
            <beat-unit>quarter</beat-unit>
            <per-minute>100</per-minute>
            </metronome>
          </direction-type>
        <sound tempo="100" />
        </direction>
      <note>
        <pitch>
          <step>A</step>
          <alter>1</alter>
          <octave>3</octave>
          </pitch>
        <duration>5040</duration>
        <type>eighth</type>
        <beam number="1">begin</beam>
        </note>
      <note>
        <pitch>
          <step>B</step>
          <octave>3</octave>
          </pitch>
        <duration>5040</duration>
        <type>eighth</type>
        <beam number="1">end</beam>
        </note>
      </measure>
    <measure number="1">
      <attributes />
      <note>
        <pitch>
          <step>C</step>
          <alter>1</alter>
          <octave>4</octave>
          </pitch>
        <duration>5040</duration>
        <type>eighth</type>
        <beam number="1">begin</beam>
        </note>
      <note>
        <pitch>
          <step>D</step>
          <alter>1</alter>
          <octave>4</octave>
          </pitch>
        <duration>5040</duration>
        <type>eighth</type>
        <beam number="1">end</beam>
        </note>
      <note>
        <pitch>
          <step>C</step>
          <alter>1</alter>
          <octave>4</octave>
          </pitch>
        <duration>5040</duration>
        <type>eighth</type>
        <beam number="1">begin</beam>
        </note>
      <note>
        <pitch>
          <step>B</step>
          <octave>3</octave>
          </pitch>
        <duration>5040</duration>
        <type>eighth</type>
        <beam number="1">end</beam>
        </note>
      <note>
        <pitch>
          <step>A</step>
          <alter>1</alter>
          <octave>3</octave>
          </pitch>
        <duration>10080</duration>
        <type>quarter</type>
        </note>
      <note>
        <pitch>
          <step>G</step>
          <alter>1</alter>
          <octave>3</octave>
          </pitch>
        <duration>5040</duration>
        <type>eighth</type>
        <beam number="1">begin</beam>
        </note>
      <note>
        <pitch>
          <step>A</step>
          <alter>1</alter>
          <octave>3</octave>
          </pitch>
        <duration>5040</duration>
        <type>eighth</type>
        <beam number="1">end</beam>
        </note>
      <barline location="right">
        <bar-style>regular</bar-style>
        </barline>
      </measure>
    <measure number="2">
      <attributes />
      <note>
        <pitch>
          <step>B</step>
          <octave>3</octave>
          </pitch>
        <duration>10080</duration>
        <type>quarter</type>
        </note>
      <note>
        <pitch>
          <step>A</step>
          <alter>1</alter>
          <octave>3</octave>
          </pitch>
        <duration>10080</duration>
        <type>quarter</type>
        </note>
      <note>
        <pitch>
          <step>B</step>
          <octave>3</octave>
          </pitch>
        <duration>10080</duration>
        <type>quarter</type>
        <notations>
          <fermata type="inverted" />
          </notations>
        </note>
      <note>
        <pitch>
          <step>G</step>
          <alter>1</alter>
          <octave>3</octave>
          </pitch>
        <duration>10080</duration>
        <type>quarter</type>
        </note>
      <barline location="right">
        <bar-style>regular</bar-style>
        </barline>
      </measure>
    <measure number="3">
      <attributes />
      <note>
        <pitch>
          <step>F</step>
          <alter>1</alter>
          <octave>3</octave>
          </pitch>
        <duration>5040</duration>
        <type>eighth</type>
        <beam number="1">begin</beam>
        </note>
      <note>
        <pitch>
          <step>G</step>
          <alter>1</alter>
          <octave>3</octave>
          </pitch>
        <duration>5040</duration>
        <type>eighth</type>
        <beam number="1">end</beam>
        </note>
      <note>
        <pitch>
          <step>A</step>
          <alter>1</alter>
          <octave>3</octave>
          </pitch>
        <duration>5040</duration>
        <type>eighth</type>
        <beam number="1">begin</beam>
        </note>
      <note>
        <pitch>
          <step>B</step>
          <octave>3</octave>
          </pitch>
        <duration>5040</duration>
        <type>eighth</type>
        <beam number="1">end</beam>
        </note>
      <note>
        <pitch>
          <step>C</step>
          <alter>1</alter>
          <octave>4</octave>
          </pitch>
        <duration>10080</duration>
        <type>quarter</type>
        </note>
      <note>
        <pitch>
          <step>D</step>
          <alter>1</alter>
          <octave>4</octave>
          </pitch>
        <duration>10080</duration>
        <type>quarter</type>
        </note>
      <barline location="right">
        <bar-style>regular</bar-style>
        </barline>
      </measure>
    <measure number="4">
      <attributes />
      <note>
        <pitch>
          <step>G</step>
          <alter>1</alter>
          <octave>3</octave>
          </pitch>
        <duration>5040</duration>
        <type>eighth</type>
        </note>
      <note>
        <pitch>
          <step>C</step>
          <alter>1</alter>
          <octave>4</octave>
          </pitch>
        <duration>10080</duration>
        <type>quarter</type>
        </note>
      <note>
        <pitch>
          <step>B</step>
          <alter>1</alter>
          <octave>3</octave>
          </pitch>
        <duration>5040</duration>
        <type>eighth</type>
        <accidental>sharp</accidental>
        </note>
      <note>
        <pitch>
          <step>C</step>
          <alter>1</alter>
          <octave>4</octave>
          </pitch>
        <duration>10080</duration>
        <type>quarter</type>
        <notations>
          <fermata type="inverted" />
          </notations>
        </note>
      <barline location="right">
        <bar-style>light-heavy</bar-style>
        </barline>
      </measure>
    <measure number="0">
      <attributes />
      <note>
        <pitch>
          <step>A</step>
          <alter>1</alter>
          <octave>3</octave>
          </pitch>
        <duration>10080</duration>
        <type>quarter</type>
        </note>
      <barline location="right">
        <bar-style>regular</bar-style>
        </barline>
      </measure>
    <measure number="5">
      <attributes />
      <note>
        <pitch>
          <step>A</step>
          <alter>1</alter>
          <octave>3</octave>
          </pitch>
        <duration>5040</duration>
        <type>eighth</type>
        <beam number="1">begin</beam>
        </note>
      <note>
        <pitch>
          <step>B</step>
          <alter>1</alter>
          <octave>3</octave>
          </pitch>
        <duration>5040</duration>
        <type>eighth</type>
        <accidental>sharp</accidental>
        <beam number="1">end</beam>
        </note>
      <note>
        <pitch>
          <step>C</step>
          <alter>1</alter>
          <octave>4</octave>
          </pitch>
        <duration>10080</duration>
        <type>quarter</type>
        </note>
      <note>
        <pitch>
          <step>B</step>
          <alter>1</alter>
          <octave>3</octave>
          </pitch>
        <duration>5040</duration>
        <type>eighth</type>
        <accidental>sharp</accidental>
        <beam number="1">begin</beam>
        </note>
      <note>
        <pitch>
          <step>A</step>
          <alter>1</alter>
          <octave>3</octave>
          </pitch>
        <duration>5040</duration>
        <type>eighth</type>
        <beam number="1">end</beam>
        </note>
      <note>
        <pitch>
          <step>G</step>
          <alter>1</alter>
          <octave>3</octave>
          </pitch>
        <duration>10080</duration>
        <type>quarter</type>
        </note>
      <barline location="right">
        <bar-style>regular</bar-style>
        </barline>
      </measure>
    <measure number="6">
      <attributes />
      <note>
        <pitch>
          <step>F</step>
          <alter>1</alter>
          <octave>3</octave>
          </pitch>
        <duration>5040</duration>
        <type>eighth</type>
        <beam number="1">begin</beam>
        </note>
      <note>
        <pitch>
          <step>C</step>
          <alter>1</alter>
          <octave>4</octave>
          </pitch>
        <duration>5040</duration>
        <type>eighth</type>
        <beam number="1">end</beam>
        </note>
      <note>
        <pitch>
          <step>B</step>
          <alter>1</alter>
          <octave>3</octave>
          </pitch>
        <duration>10080</duration>
        <type>quarter</type>
        <accidental>sharp</accidental>
        </note>
      <note>
        <pitch>
          <step>C</step>
          <alter>1</alter>
          <octave>4</octave>
          </pitch>
        <duration>10080</duration>
        <type>quarter</type>
        <notations>
          <fermata type="inverted" />
          </notations>
        </note>
      <note>
        <pitch>
          <step>A</step>
          <alter>1</alter>
          <octave>3</octave>
          </pitch>
        <duration>5040</duration>
        <type>eighth</type>
        <beam number="1">begin</beam>
        </note>
      <note>
        <pitch>
          <step>B</step>
          <alter>0</alter>
          <octave>3</octave>
          </pitch>
        <duration>5040</duration>
        <type>eighth</type>
        <accidental>natural</accidental>
        <beam number="1">end</beam>
        </note>
      <barline location="right">
        <bar-style>regular</bar-style>
        </barline>
      </measure>
    <measure number="7">
      <attributes />
      <note>
        <pitch>
          <step>C</step>
          <alter>1</alter>
          <octave>4</octave>
          </pitch>
        <duration>10080</duration>
        <type>quarter</type>
        </note>
      <note>
        <pitch>
          <step>F</step>
          <alter>1</alter>
          <octave>4</octave>
          </pitch>
        <duration>5040</duration>
        <type>eighth</type>
        <beam number="1">begin</beam>
        </note>
      <note>
        <pitch>
          <step>E</step>
          <alter>1</alter>
          <octave>4</octave>
          </pitch>
        <duration>5040</duration>
        <type>eighth</type>
        <beam number="1">end</beam>
        </note>
      <note>
        <pitch>
          <step>D</step>
          <alter>1</alter>
          <octave>4</octave>
          </pitch>
        <duration>10080</duration>
        <type>quarter</type>
        </note>
      <note>
        <pitch>
          <step>D</step>
          <alter>1</alter>
          <octave>4</octave>
          </pitch>
        <duration>10080</duration>
        <type>quarter</type>
        </note>
      <barline location="right">
        <bar-style>regular</bar-style>
        </barline>
      </measure>
    <measure number="8">
      <attributes />
      <note>
        <pitch>
          <step>G</step>
          <alter>1</alter>
          <octave>3</octave>
          </pitch>
        <duration>5040</duration>
        <type>eighth</type>
        <beam number="1">begin</beam>
        </note>
      <note>
        <pitch>
          <step>A</step>
          <alter>1</alter>
          <octave>3</octave>
          </pitch>
        <duration>5040</duration>
        <type>eighth</type>
        <beam number="1">end</beam>
        </note>
      <note>
        <pitch>
          <step>B</step>
          <octave>3</octave>
          </pitch>
        <duration>5040</duration>
        <type>eighth</type>
        <beam number="1">begin</beam>
        </note>
      <note>
        <pitch>
          <step>C</step>
          <alter>1</alter>
          <octave>4</octave>
          </pitch>
        <duration>5040</duration>
        <type>eighth</type>
        <beam number="1">end</beam>
        </note>
      <note>
        <pitch>
          <step>D</step>
          <alter>1</alter>
          <octave>4</octave>
          </pitch>
        <duration>10080</duration>
        <type>quarter</type>
        <notations>
          <fermata type="inverted" />
          </notations>
        </note>
      <note>
        <pitch>
          <step>C</step>
          <alter>1</alter>
          <octave>4</octave>
          </pitch>
        <duration>10080</duration>
        <type>quarter</type>
        </note>
      <barline location="right">
        <bar-style>regular</bar-style>
        </barline>
      </measure>
    <measure number="9">
      <attributes />
      <note>
        <pitch>
          <step>C</step>
          <alter>1</alter>
          <octave>4</octave>
          </pitch>
        <duration>10080</duration>
        <type>quarter</type>
        </note>
      <note>
        <pitch>
          <step>F</step>
          <alter>1</alter>
          <octave>3</octave>
          </pitch>
        <duration>5040</duration>
        <type>eighth</type>
        <beam number="1">begin</beam>
        </note>
      <note>
        <pitch>
          <step>G</step>
          <alter>1</alter>
          <octave>3</octave>
          </pitch>
        <duration>5040</duration>
        <type>eighth</type>
        <beam number="1">end</beam>
        </note>
      <note>
        <pitch>
          <step>A</step>
          <alter>1</alter>
          <octave>3</octave>
          </pitch>
        <duration>5040</duration>
        <type>eighth</type>
        <beam number="1">begin</beam>
        </note>
      <note>
        <pitch>
          <step>B</step>
          <octave>3</octave>
          </pitch>
        <duration>5040</duration>
        <type>eighth</type>
        <beam number="1">end</beam>
        </note>
      <note>
        <pitch>
          <step>C</step>
          <alter>1</alter>
          <octave>4</octave>
          </pitch>
        <duration>10080</duration>
        <type>quarter</type>
        </note>
      <barline location="right">
        <bar-style>regular</bar-style>
        </barline>
      </measure>
    <measure number="10">
      <attributes />
      <note>
        <pitch>
          <step>B</step>
          <octave>3</octave>
          </pitch>
        <duration>5040</duration>
        <type>eighth</type>
        <beam number="1">begin</beam>
        </note>
      <note>
        <pitch>
          <step>A</step>
          <alter>1</alter>
          <octave>3</octave>
          </pitch>
        <duration>5040</duration>
        <type>eighth</type>
        <beam number="1">end</beam>
        </note>
      <note>
        <pitch>
          <step>G</step>
          <alter>1</alter>
          <octave>3</octave>
          </pitch>
        <duration>10080</duration>
        <type>quarter</type>
        </note>
      <note>
        <pitch>
          <step>F</step>
          <alter>1</alter>
          <octave>3</octave>
          </pitch>
        <duration>10080</duration>
        <type>quarter</type>
        <notations>
          <fermata type="inverted" />
          </notations>
        </note>
      <barline location="right">
        <bar-style>light-light</bar-style>
        </barline>
      </measure>
    </part>
  <part id="P151db4fe8fcd469a0e65634288de4e99">
    <measure number="0">
      <attributes>
        <divisions>10080</divisions>
        <key>
          <fifths>6</fifths>
          </key>
        <time>
          <beats>4</beats>
          <beat-type>4</beat-type>
          </time>
        <clef>
          <sign>F</sign>
          <line>4</line>
          </clef>
        </attributes>
      <direction>
        <direction-type>
          <metronome parentheses="no">
            <beat-unit>quarter</beat-unit>
            <per-minute>100</per-minute>
            </metronome>
          </direction-type>
        <sound tempo="100" />
        </direction>
      <note>
        <pitch>
          <step>F</step>
          <alter>1</alter>
          <octave>3</octave>
          </pitch>
        <duration>10080</duration>
        <type>quarter</type>
        </note>
      </measure>
    <measure number="1">
      <attributes />
      <note>
        <pitch>
          <step>A</step>
          <alter>1</alter>
          <octave>2</octave>
          </pitch>
        <duration>5040</duration>
        <type>eighth</type>
        <beam number="1">begin</beam>
        </note>
      <note>
        <pitch>
          <step>B</step>
          <octave>2</octave>
          </pitch>
        <duration>5040</duration>
        <type>eighth</type>
        <beam number="1">end</beam>
        </note>
      <note>
        <pitch>
          <step>C</step>
          <alter>1</alter>
          <octave>3</octave>
          </pitch>
        <duration>10080</duration>
        <type>quarter</type>
        </note>
      <note>
        <pitch>
          <step>F</step>
          <alter>1</alter>
          <octave>2</octave>
          </pitch>
        <duration>10080</duration>
        <type>quarter</type>
        </note>
      <note>
        <pitch>
          <step>C</step>
          <alter>1</alter>
          <octave>3</octave>
          </pitch>
        <duration>10080</duration>
        <type>quarter</type>
        </note>
      <barline location="right">
        <bar-style>regular</bar-style>
        </barline>
      </measure>
    <measure number="2">
      <attributes />
      <note>
        <pitch>
          <step>D</step>
          <alter>1</alter>
          <octave>3</octave>
          </pitch>
        <duration>5040</duration>
        <type>eighth</type>
        <beam number="1">begin</beam>
        </note>
      <note>
        <pitch>
          <step>E</step>
          <alter>0</alter>
          <octave>3</octave>
          </pitch>
        <duration>5040</duration>
        <type>eighth</type>
        <accidental>natural</accidental>
        <beam number="1">end</beam>
        </note>
      <note>
        <pitch>
          <step>F</step>
          <alter>1</alter>
          <octave>3</octave>
          </pitch>
        <duration>10080</duration>
        <type>quarter</type>
        </note>
      <note>
        <pitch>
          <step>G</step>
          <alter>1</alter>
          <octave>3</octave>
          </pitch>
        <duration>10080</duration>
        <type>quarter</type>
        <notations>
          <fermata type="inverted" />
          </notations>
        </note>
      <note>
        <pitch>
          <step>E</step>
          <alter>1</alter>
          <octave>3</octave>
          </pitch>
        <duration>10080</duration>
        <type>quarter</type>
        <accidental>sharp</accidental>
        </note>
      <barline location="right">
        <bar-style>regular</bar-style>
        </barline>
      </measure>
    <measure number="3">
      <attributes />
      <note>
        <pitch>
          <step>F</step>
          <alter>1</alter>
          <octave>3</octave>
          </pitch>
        <duration>10080</duration>
        <type>quarter</type>
        </note>
      <note>
        <pitch>
          <step>F</step>
          <alter>1</alter>
          <octave>2</octave>
          </pitch>
        <duration>10080</duration>
        <type>quarter</type>
        </note>
      <note>
        <pitch>
          <step>F</step>
          <alter>1</alter>
          <octave>3</octave>
          </pitch>
        <duration>5040</duration>
        <type>eighth</type>
        <beam number="1">begin</beam>
        </note>
      <note>
        <pitch>
          <step>E</step>
          <alter>1</alter>
          <octave>3</octave>
          </pitch>
        <duration>5040</duration>
        <type>eighth</type>
        <beam number="1">end</beam>
        </note>
      <note>
        <pitch>
          <step>D</step>
          <alter>1</alter>
          <octave>3</octave>
          </pitch>
        <duration>10080</duration>
        <type>quarter</type>
        </note>
      <barline location="right">
        <bar-style>regular</bar-style>
        </barline>
      </measure>
    <measure number="4">
      <attributes />
      <note>
        <pitch>
          <step>C</step>
          <alter>1</alter>
          <octave>3</octave>
          </pitch>
        <duration>10080</duration>
        <type>quarter</type>
        </note>
      <note>
        <pitch>
          <step>G</step>
          <alter>1</alter>
          <octave>2</octave>
          </pitch>
        <duration>10080</duration>
        <type>quarter</type>
        </note>
      <note>
        <pitch>
          <step>C</step>
          <alter>1</alter>
          <octave>3</octave>
          </pitch>
        <duration>10080</duration>
        <type>quarter</type>
        <notations>
          <fermata type="inverted" />
          </notations>
        </note>
      <barline location="right">
        <bar-style>light-heavy</bar-style>
        </barline>
      </measure>
    <measure number="0">
      <attributes />
      <note>
        <pitch>
          <step>F</step>
          <alter>1</alter>
          <octave>3</octave>
          </pitch>
        <duration>5040</duration>
        <type>eighth</type>
        <beam number="1">begin</beam>
        </note>
      <note>
        <pitch>
          <step>E</step>
          <alter>1</alter>
          <octave>3</octave>
          </pitch>
        <duration>5040</duration>
        <type>eighth</type>
        <beam number="1">end</beam>
        </note>
      <barline location="right">
        <bar-style>regular</bar-style>
        </barline>
      </measure>
    <measure number="5">
      <attributes />
      <note>
        <pitch>
          <step>D</step>
          <alter>1</alter>
          <octave>3</octave>
          </pitch>
        <duration>10080</duration>
        <type>quarter</type>
        </note>
      <note>
        <pitch>
          <step>E</step>
          <alter>1</alter>
          <octave>3</octave>
          </pitch>
        <duration>5040</duration>
        <type>eighth</type>
        <beam number="1">begin</beam>
        </note>
      <note>
        <pitch>
          <step>F</step>
          <alter>1</alter>
          <octave>3</octave>
          </pitch>
        <duration>5040</duration>
        <type>eighth</type>
        <beam number="1">end</beam>
        </note>
      <note>
        <pitch>
          <step>G</step>
          <alter>1</alter>
          <octave>3</octave>
          </pitch>
        <duration>10080</duration>
        <type>quarter</type>
        </note>
      <note>
        <pitch>
          <step>C</step>
          <alter>1</alter>
          <octave>3</octave>
          </pitch>
        <duration>5040</duration>
        <type>eighth</type>
        <beam number="1">begin</beam>
        </note>
      <note>
        <pitch>
          <step>B</step>
          <alter>1</alter>
          <octave>2</octave>
          </pitch>
        <duration>5040</duration>
        <type>eighth</type>
        <accidental>sharp</accidental>
        <beam number="1">end</beam>
        </note>
      <barline location="right">
        <bar-style>regular</bar-style>
        </barline>
      </measure>
    <measure number="6">
      <attributes />
      <note>
        <pitch>
          <step>A</step>
          <alter>1</alter>
          <octave>2</octave>
          </pitch>
        <duration>5040</duration>
        <type>eighth</type>
        <beam number="1">begin</beam>
        </note>
      <note>
        <pitch>
          <step>G</step>
          <alter>1</alter>
          <octave>2</octave>
          </pitch>
        <duration>5040</duration>
        <type>eighth</type>
        <beam number="1">end</beam>
        </note>
      <note>
        <pitch>
          <step>G</step>
          <alter>1</alter>
          <octave>2</octave>
          </pitch>
        <duration>10080</duration>
        <type>quarter</type>
        </note>
      <note>
        <pitch>
          <step>C</step>
          <alter>1</alter>
          <octave>3</octave>
          </pitch>
        <duration>10080</duration>
        <type>quarter</type>
        <notations>
          <fermata type="inverted" />
          </notations>
        </note>
      <note>
        <pitch>
          <step>F</step>
          <alter>1</alter>
          <octave>3</octave>
          </pitch>
        <duration>10080</duration>
        <type>quarter</type>
        </note>
      <barline location="right">
        <bar-style>regular</bar-style>
        </barline>
      </measure>
    <measure number="7">
      <attributes />
      <note>
        <pitch>
          <step>F</step>
          <alter>1</alter>
          <octave>2</octave>
          </pitch>
        <duration>5040</duration>
        <type>eighth</type>
        <beam number="1">begin</beam>
        </note>
      <note>
        <pitch>
          <step>G</step>
          <alter>1</alter>
          <octave>2</octave>
          </pitch>
        <duration>5040</duration>
        <type>eighth</type>
        <beam number="1">end</beam>
        </note>
      <note>
        <pitch>
          <step>A</step>
          <alter>1</alter>
          <octave>2</octave>
          </pitch>
        <duration>10080</duration>
        <type>quarter</type>
        </note>
      <note>
        <pitch>
          <step>B</step>
          <octave>2</octave>
          </pitch>
        <duration>5040</duration>
        <type>eighth</type>
        <beam number="1">begin</beam>
        </note>
      <note>
        <pitch>
          <step>C</step>
          <alter>1</alter>
          <octave>3</octave>
          </pitch>
        <duration>5040</duration>
        <type>eighth</type>
        <beam number="1">end</beam>
        </note>
      <note>
        <pitch>
          <step>D</step>
          <alter>1</alter>
          <octave>3</octave>
          </pitch>
        <duration>10080</duration>
        <type>quarter</type>
        </note>
      <barline location="right">
        <bar-style>regular</bar-style>
        </barline>
      </measure>
    <measure number="8">
      <attributes />
      <note>
        <pitch>
          <step>E</step>
          <alter>1</alter>
          <octave>3</octave>
          </pitch>
        <duration>5040</duration>
        <type>eighth</type>
        <beam number="1">begin</beam>
        </note>
      <note>
        <pitch>
          <step>F</step>
          <alter>2</alter>
          <octave>3</octave>
          </pitch>
        <duration>5040</duration>
        <type>eighth</type>
        <accidental>double-sharp</accidental>
        <beam number="1">end</beam>
        </note>
      <note>
        <pitch>
          <step>G</step>
          <alter>1</alter>
          <octave>3</octave>
          </pitch>
        <duration>10080</duration>
        <type>quarter</type>
        </note>
      <note>
        <pitch>
          <step>D</step>
          <alter>1</alter>
          <octave>3</octave>
          </pitch>
        <duration>10080</duration>
        <type>quarter</type>
        <notations>
          <fermata type="inverted" />
          </notations>
        </note>
      <note>
        <pitch>
          <step>A</step>
          <alter>1</alter>
          <octave>2</octave>
          </pitch>
        <duration>5040</duration>
        <type>eighth</type>
        <beam number="1">begin</beam>
        </note>
      <note>
        <pitch>
          <step>B</step>
          <octave>2</octave>
          </pitch>
        <duration>5040</duration>
        <type>eighth</type>
        <beam number="1">end</beam>
        </note>
      <barline location="right">
        <bar-style>regular</bar-style>
        </barline>
      </measure>
    <measure number="9">
      <attributes />
      <note>
        <pitch>
          <step>C</step>
          <alter>1</alter>
          <octave>3</octave>
          </pitch>
        <duration>10080</duration>
        <type>quarter</type>
        </note>
      <note>
        <pitch>
          <step>D</step>
          <alter>1</alter>
          <octave>3</octave>
          </pitch>
        <duration>5040</duration>
        <type>eighth</type>
        <beam number="1">begin</beam>
        </note>
      <note>
        <pitch>
          <step>E</step>
          <alter>1</alter>
          <octave>3</octave>
          </pitch>
        <duration>5040</duration>
        <type>eighth</type>
        <beam number="1">end</beam>
        </note>
      <note>
        <pitch>
          <step>F</step>
          <alter>1</alter>
          <octave>3</octave>
          </pitch>
        <duration>10080</duration>
        <type>quarter</type>
        <accidental>sharp</accidental>
        </note>
      <note>
        <pitch>
          <step>E</step>
          <alter>1</alter>
          <octave>3</octave>
          </pitch>
        <duration>5040</duration>
        <type>eighth</type>
        <beam number="1">begin</beam>
        </note>
      <note>
        <pitch>
          <step>F</step>
          <alter>1</alter>
          <octave>3</octave>
          </pitch>
        <duration>5040</duration>
        <type>eighth</type>
        <beam number="1">end</beam>
        </note>
      <barline location="right">
        <bar-style>regular</bar-style>
        </barline>
      </measure>
    <measure number="10">
      <attributes />
      <note>
        <pitch>
          <step>G</step>
          <alter>1</alter>
          <octave>3</octave>
          </pitch>
        <duration>10080</duration>
        <type>quarter</type>
        </note>
      <note>
        <pitch>
          <step>C</step>
          <alter>1</alter>
          <octave>3</octave>
          </pitch>
        <duration>10080</duration>
        <type>quarter</type>
        </note>
      <note>
        <pitch>
          <step>F</step>
          <alter>1</alter>
          <octave>2</octave>
          </pitch>
        <duration>10080</duration>
        <type>quarter</type>
        <notations>
          <fermata type="inverted" />
          </notations>
        </note>
      <barline location="right">
        <bar-style>light-light</bar-style>
        </barline>
      </measure>
    </part>
  </score-partwise>
